Workbook

Sheet TOP客户累计改善清单
B2: 1.表格列宽不能超过2个中文字节或者4个英文字节（最多不能超3中文字节或6英文字节，序号只能1中文字节2个英文字节内）； 2.列宽超过的，获得大象眼睛奖并做检讨，且和晋级/晋升/敬业度考核等绑定。
B3: 发运超时商家维度-TOP客户改善名单累计表
B4: 数据来源:T-1全链路管家报表-抖音/淘天→发货-揽收超时/揽收-发运超时→客户层； 商家端结合虚假轨迹管控要求 ：近7天上榜次数超3次，关闭商家“揽收兜底”使用权限。
B5: 3 | C5: 3 | D5: 3 | E5: 8 | F5: 10 | G5: 6 | H5: 2 | J5: 2 | K5: 2 | L5: 3 | M5: 3 | N5: 3 | O5: 3 | P5: 3 | Q5: 3 | R5: 3 | S5: 3 | T5: 8 | U5: 8 | V5: 3 | W5: 2
B6: 上榜日期 | C6: 省 | D6: 分部名称 | E6: 唯一值（分部名称+客户名称+客户编码 | F6: 客户名称 | G6: 客户编码 | H6: 是否配置发运兜底 | I6: 一级积分清退次数 | J6: 平台 | K6: 上榜次数 | L6: 揽收-发运超时 | T6: 超时原因 | U6: 整改动作 | V6: 达成日期 | W6: 是否达成
L7: 抖音平台 | P7: 淘天平台
L8: 超24h | M8: 超36h | O8: 超48h | P8: 超24h | Q8: 超36h | S8: 超48h
L9: 票件量 | M9: 单量 | N9: 超时率 | O9: 票件量 | P9: 票件量 | Q9: 单量 | R9: 超时率 | S9: 票件量
B10: 46092 | C10: 杭州 | D10: 浙江杭州萧山区新塘公司 | E10: 浙江杭州萧山区新塘公司红宝石分部-沐洛311420786786 | F10: 红宝石分部-沐洛 | G10: 311420786786 | H10: 今日已关闭揽收兜底 | I10: =_xlfn.IFNA(_xlfn.XLOOKUP(_xlfn.XLOOKUP(D10,上榜过且清退过的网点!H:H,上榜过且清退过的网点!I:I),上榜过且清退过的网点!A:A,上榜过且清退过的网点!D:D),0) -> 0 | J10: 淘天 | K10: 7 | L10: 0 | M10: 0 | N10: 0 | O10: 0 | P10: 2229 | Q10: 1711 | R10: 18.48% | S10: 806 | T10: 客户缺货 | U10: 72H交不出做退回 | V10: - | W10: -
B11: 46092 | C11: 苏州 | D11: 江苏南通海门国际家纺城公司天补分部 | E11: 江苏南通海门国际家纺城公司天补分部888279华诺(唯客)102342100146 | F11: 888279华诺(唯客) | G11: 102342100146 | I11: =_xlfn.IFNA(_xlfn.XLOOKUP(_xlfn.XLOOKUP(D11,上榜过且清退过的网点!H:H,上榜过且清退过的网点!I:I),上榜过且清退过的网点!A:A,上榜过且清退过的网点!D:D),0) -> 0 | J11: 淘天 | K11: 1 | L11: 2 | M11: 1 | N11: 0.25% | O11: 1 | P11: 2722 | Q11: 1589 | R11: 32.15% | S11: 29 | T11: 客户缺货 | U11: 超36小时的订单做始发退回 | V11: 46096 | W11: -
B12: 46092 | C12: 广佛中 | D12: 广东广州从化区公司汽博服务部 | E12: 广东广州从化区公司汽博服务部维特丝洗护旗舰店迪仕曼旗舰店-小红书京东淘宝-钟落潭维特丝102358210069 | F12: 维特丝洗护旗舰店迪仕曼旗舰店-小红书京东淘宝-钟落潭维特丝 | G12: 102358210069 | I12: =_xlfn.IFNA(_xlfn.XLOOKUP(_xlfn.XLOOKUP(D12,上榜过且清退过的网点!H:H,上榜过且清退过的网点!I:I),上榜过且清退过的网点!A:A,上榜过且清退过的网点!D:D),0) -> 0 | J12: 淘天 | K12: 1 | L12: 0 | M12: 0 | N12: 0 | O12: 0 | P12: 1781 | Q12: 1086 | R12: 3.6% | S12: 352 | T12: 客户缺货 | U12: - | V12: 46096 | W12: -
B13: 46092 | C13: 义乌 | D13: 浙江义乌稠江汇通路公司物流园服务部 | E13: 浙江义乌稠江汇通路公司物流园服务部菜鸟仓c2m----tb62883211322003 | F13: 菜鸟仓c2m----tb6288 | G13: 3211322003 | I13: =_xlfn.IFNA(_xlfn.XLOOKUP(_xlfn.XLOOKUP(D13,上榜过且清退过的网点!H:H,上榜过且清退过的网点!I:I),上榜过且清退过的网点!A:A,上榜过且清退过的网点!D:D),0) -> 0 | J13: 淘天 | K13: 2 | L13: 0 | M13: 0 | N13: 0 | O13: 0 | P13: 1348 | Q13: 1008 | R13: 0.86% | S13: 475 | T13: 商家打包不出来 | U13: 超36小时的订单做始发退回 | V13: 46096 | W13: -
B14: 46092 | C14: 南京 | D14: 江苏南京浦口区新城公司 | E14: 江苏南京浦口区新城公司凤凰新华书店211149548426 | F14: 凤凰新华书店 | G14: 211149548426 | H14: 今日已关闭揽收兜底 | I14: =_xlfn.IFNA(_xlfn.XLOOKUP(_xlfn.XLOOKUP(D14,上榜过且清退过的网点!H:H,上榜过且清退过的网点!I:I),上榜过且清退过的网点!A:A,上榜过且清退过的网点!D:D),0) -> 0 | J14: 淘天 | K14: 4 | L14: 5 | M14: 4 | N14: 0.84% | O14: 4 | P14: 915 | Q14: 846 | R14: 2.53% | S14: 494 | T14: 国营企业，9点之后一直在揽收又交不到分拨中心，考核一直有但是网点没改善 | U14: 省总对接拉群采取措施解决 | V14: - | W14: -
B15: 46092 | C15: 海南 | D15: 海南东方市公司 | E15: 海南东方市公司执vKS570342662455 | F15: 执vKS | G15: 570342662455 | I15: =_xlfn.IFNA(_xlfn.XLOOKUP(_xlfn.XLOOKUP(D15,上榜过且清退过的网点!H:H,上榜过且清退过的网点!I:I),上榜过且清退过的网点!A:A,上榜过且清退过的网点!D:D),0) -> 0 | J15: 抖音 | K15: 1 | L15: 3819 | M15: 2245 | N15: 39.12% | O15: 2160 | P15: 0 | Q15: 0 | R15: 0 | S15: 0 | T15: 客户缺货 | U15: 已关闭批里揽收，目前是手动揽收，已告知超时之前做始发退回，不允许超时 | V15: 46094 | W15: -
B16: 46092 | C16: 河南 | D16: 河南鹿邑县公司涡北镇物流园分部 | E16: 河南鹿邑县公司涡北镇物流园分部管阳仓25279351394 | F16: 管阳仓2 | G16: 5279351394 | I16: =_xlfn.IFNA(_xlfn.XLOOKUP(_xlfn.XLOOKUP(D16,上榜过且清退过的网点!H:H,上榜过且清退过的网点!I:I),上榜过且清退过的网点!A:A,上榜过且清退过的网点!D:D),0) -> 1 | J16: 抖音 | K16: 1 | L16: 1990 | M16: 1908 | N16: 17.89% | O16: 30 | P16: 28 | Q16: 26 | R16: 18.18% | S16: 1 | T16: 缺货客户，发花茶,日均两万单且交货太晚,导致跟不上车 | U16: 今天不再给客户充值单号,以免形成恶性循环。旧单全部清完再发货。 | V16: 46095 | W16: -
B17: 46092 | C17: 揭阳 | D17: 广东汕头潮南新两英公司 | E17: 广东汕头潮南新两英公司予棉内衣-KH-燕雯678825346921 | F17: 予棉内衣-KH-燕雯 | G17: 678825346921 | I17: =_xlfn.IFNA(_xlfn.XLOOKUP(_xlfn.XLOOKUP(D17,上榜过且清退过的网点!H:H,上榜过且清退过的网点!I:I),上榜过且清退过的网点!A:A,上榜过且清退过的网点!D:D),0) -> 0 | J17: 抖音 | K17: 1 | L17: 1987 | M17: 1822 | N17: 56.99% | O17: 209 | P17: 0 | Q17: 0 | R17: 0 | S17: 0 | T17: 商家缺货 | U17: 已通知厂家增加人手生产 | V17: 46097 | W17: -
B18: 46092 | C18: 湖北 | D18: 湖北潜江公司艾草分部 | E18: 湖北潜江公司艾草分部刘俊-梵悦VanJoy446790202501 | F18: 刘俊-梵悦VanJoy | G18: 446790202501 | I18: =_xlfn.IFNA(_xlfn.XLOOKUP(_xlfn.XLOOKUP(D18,上榜过且清退过的网点!H:H,上榜过且清退过的网点!I:I),上榜过且清退过的网点!A:A,上榜过且清退过的网点!D:D),0) -> 1 | J18: 抖音 | K18: 1 | L18: 1736 | M18: 1608 | N18: 73.63% | O18: 0 | P18: 0 | Q18: 0 | R18: 0 | S18: 0 | T18: 商家缺货 | U18: 催促客户及时给货 | V18: 46096 | W18: -
B19: 46092 | C19: 广佛中 | D19: 广东广州花都区新雅公司利佳分部 | E19: 广东广州花都区新雅公司利佳分部P93-穆辛女装-抖音-赵总678459100181 | F19: P93-穆辛女装-抖音-赵总 | G19: 678459100181 | I19: =_xlfn.IFNA(_xlfn.XLOOKUP(_xlfn.XLOOKUP(D19,上榜过且清退过的网点!H:H,上榜过且清退过的网点!I:I),上榜过且清退过的网点!A:A,上榜过且清退过的网点!D:D),0) -> 2 | J19: 抖音 | K19: 2 | L19: 1412 | M19: 1277 | N19: - | O19: 834 | P19: 0 | Q19: 0 | R19: 0 | S19: 0 | T19: 服装客户，日均2万票，缺货 | U19: 客户同意做始发退回换单发，网点现在做超36H交件的 | V19: 46096 | W19: -
B20: 46093 | C20: 揭阳 | D20: 广东汕头潮南新两英公司 | E20: 广东汕头潮南新两英公司予棉内衣-KH-燕雯678825346921 | F20: 予棉内衣-KH-燕雯 | G20: 678825346921 | I20: =_xlfn.IFNA(_xlfn.XLOOKUP(_xlfn.XLOOKUP(D20,上榜过且清退过的网点!H:H,上榜过且清退过的网点!I:I),上榜过且清退过的网点!A:A,上榜过且清退过的网点!D:D),0) -> 0 | J20: 抖音 | K20: 2 | L20: 4145 | M20: 4037 | N20: 59.53% | O20: 68 | P20: 0 | Q20: 0 | R20: 0 | S20: 0 | T20: 商家缺货 | U20: 已通知厂家增加人手生产 | V20: 46097 | W20: -
B21: 46093 | C21: 深莞惠 | D21: 广东东莞新企石公司 | E21: 广东东莞新企石公司张小军588063778008 | F21: 张小军 | G21: 588063778008 | I21: =_xlfn.IFNA(_xlfn.XLOOKUP(_xlfn.XLOOKUP(D21,上榜过且清退过的网点!H:H,上榜过且清退过的网点!I:I),上榜过且清退过的网点!A:A,上榜过且清退过的网点!D:D),0) -> 0 | J21: 抖音 | K21: 1 | L21: 3070 | M21: 2812 | N21: 35.16% | O21: 20 | P21: 5 | Q21: 2 | R21: 22.22% | S21: 2 | T21: 客户发件延误 | U21: 省区拉群对接督促客户12h内交件 | V21: 46096 | W21: -
B22: 46093 | C22: 海南 | D22: 海南东方市公司 | E22: 海南东方市公司执vKS570342662455 | F22: 执vKS | G22: 570342662455 | I22: =_xlfn.IFNA(_xlfn.XLOOKUP(_xlfn.XLOOKUP(D22,上榜过且清退过的网点!H:H,上榜过且清退过的网点!I:I),上榜过且清退过的网点!A:A,上榜过且清退过的网点!D:D),0) -> 0 | J22: 抖音 | K22: 2 | L22: 2244 | M22: 2035 | N22: 75.48% | O22: 2035 | P22: 0 | Q22: 0 | R22: 0 | S22: 0 | T22: 客户缺货 | U22: 已关闭批里揽收，目前是手动揽收，已告知超时之前做始发退回，不允许超时 | V22: 46094 | W22: -
B23: 46093 | C23: 苏州 | D23: 江苏苏州常熟市招商城公司华联服务部 | E23: 江苏苏州常熟市招商城公司华联服务部聚福-蓝续服饰484398576648 | F23: 聚福-蓝续服饰 | G23: 484398576648 | H23: 是 | I23: =_xlfn.IFNA(_xlfn.XLOOKUP(_xlfn.XLOOKUP(D23,上榜过且清退过的网点!H:H,上榜过且清退过的网点!I:I),上榜过且清退过的网点!A:A,上榜过且清退过的网点!D:D),0) -> 0 | J23: 抖音 | K23: 1 | L23: 2283 | M23: 1656 | N23: 6.18% | O23: 183 | P23: 6 | Q23: 6 | R23: 6.52% | S23: 3 | T23: 商家突然爆单，工厂供货不及时导致的 | U23: 已经督促这两天陆续都会发掉 | V23: 46096 | W23: -
B24: 46093 | C24: 湖北 | D24: 湖北潜江公司艾草分部 | E24: 湖北潜江公司艾草分部刘俊-梵悦VanJoy446790202501 | F24: 刘俊-梵悦VanJoy | G24: 446790202501 | H24: 是 | I24: =_xlfn.IFNA(_xlfn.XLOOKUP(_xlfn.XLOOKUP(D24,上榜过且清退过的网点!H:H,上榜过且清退过的网点!I:I),上榜过且清退过的网点!A:A,上榜过且清退过的网点!D:D),0) -> 1 | J24: 抖音 | K24: 2 | L24: 1487 | M24: 1464 | N24: 58.84% | O24: 617 | P24: 0 | Q24: 0 | R24: 0 | S24: 0 | T24: 商家缺货 | U24: 催促客户及时给货 | V24: 46096 | W24: -
B25: 46093 | C25: 贵州 | D25: 贵州习水县公司 | E25: 贵州习水县公司周陆军5646004933 | F25: 周陆军 | G25: 5646004933 | I25: =_xlfn.IFNA(_xlfn.XLOOKUP(_xlfn.XLOOKUP(D25,上榜过且清退过的网点!H:H,上榜过且清退过的网点!I:I),上榜过且清退过的网点!A:A,上榜过且清退过的网点!D:D),0) -> 0 | J25: 淘天 | K25: 3 | L25: 0 | M25: 0 | N25: 0 | O25: 0 | P25: 4780 | Q25: 4780 | R25: 100% | S25: 0 | T25: 打单后商家货源不够 | U25: 通知商家改善，按时交件发出 | V25: 46096 | W25: -
B26: 46093 | C26: 杭州 | D26: 浙江杭州萧山区新塘公司 | E26: 浙江杭州萧山区新塘公司红宝石分部-沐洛311420786786 | F26: 红宝石分部-沐洛 | G26: 311420786786 | H26: 是 | I26: =_xlfn.IFNA(_xlfn.XLOOKUP(_xlfn.XLOOKUP(D26,上榜过且清退过的网点!H:H,上榜过且清退过的网点!I:I),上榜过且清退过的网点!A:A,上榜过且清退过的网点!D:D),0) -> 0 | J26: 淘天 | K26: 7 | L26: 0 | M26: 0 | N26: 0 | O26: 0 | P26: 2366 | Q26: 1795 | R26: 20.53% | S26: 911 | T26: 客户缺货 | U26: 72H交不出做退回 | V26: - | W26: -
B27: 46093 | C27: 南京 | D27: 江苏南京浦口区新城公司 | E27: 江苏南京浦口区新城公司凤凰新华书店211149548426 | F27: 凤凰新华书店 | G27: 211149548426 | H27: 是 | I27: =_xlfn.IFNA(_xlfn.XLOOKUP(_xlfn.XLOOKUP(D27,上榜过且清退过的网点!H:H,上榜过且清退过的网点!I:I),上榜过且清退过的网点!A:A,上榜过且清退过的网点!D:D),0) -> 0 | J27: 淘天 | K27: 5 | L27: 3 | M27: 2 | N27: 0.41% | O27: 2 | P27: 1717 | Q27: 1614 | R27: 5.57% | S27: 1553 | T27: 国营企业，9点之后一直在揽收又交不到分拨中心，考核一直有但是网点没改善 | U27: 省总对接拉群采取措施解决 | V27: - | W27: -
B28: 46093 | C28: 湖北 | D28: 湖北营销市场部 | E28: 湖北营销市场部好礼云仓392472329696 | F28: 好礼云仓 | G28: 392472329696 | H28: 是 | I28: =_xlfn.IFNA(_xlfn.XLOOKUP(_xlfn.XLOOKUP(D28,上榜过且清退过的网点!H:H,上榜过且清退过的网点!I:I),上榜过且清退过的网点!A:A,上榜过且清退过的网点!D:D),0) -> 0 | J28: 淘天 | K28: 1 | L28: 0 | M28: 0 | N28: 0 | O28: 0 | P28: 3087 | Q28: 652 | R28: 5.09% | S28: 106 | T28: 分拨滞留 | U28: 已解决 | V28: 46094 | W28: -
B29: 46093 | C29: 贵州 | D29: 贵州贵阳南明青年路公司 | E29: 贵州贵阳南明青年路公司刘少云551614677629 | F29: 刘少云 | G29: 551614677629 | I29: =_xlfn.IFNA(_xlfn.XLOOKUP(_xlfn.XLOOKUP(D29,上榜过且清退过的网点!H:H,上榜过且清退过的网点!I:I),上榜过且清退过的网点!A:A,上榜过且清退过的网点!D:D),0) -> 0 | J29: 淘天 | K29: 1 | L29: 0 | M29: 0 | N29: 0 | O29: 0 | P29: 640 | Q29: 640 | R29: 100% | S29: 0 | T29: 打单后商家货源不够 | U29: 通知商家改善，按时交件发出 | V29: 46096 | W29: -
B30: 46094 | C30: 广佛中 | D30: 广东广州增城新塘白江村公司东洲服务部 | E30: 广东广州增城新塘白江村公司东洲服务部100812慕至尚服饰-李威客户459740100812 | F30: 100812慕至尚服饰-李威客户 | G30: 459740100812 | H30: 是 | I30: =_xlfn.IFNA(_xlfn.XLOOKUP(_xlfn.XLOOKUP(D30,上榜过且清退过的网点!H:H,上榜过且清退过的网点!I:I),上榜过且清退过的网点!A:A,上榜过且清退过的网点!D:D),0) -> 0 | J30: 抖音 | K30: 1 | L30: 3347 | M30: 2645 | N30: 23.5% | O30: 1820 | P30: 0 | Q30: 0 | R30: 0 | S30: 0 | T30: 服装客户缺货 | U30: 后续超时部分及时通 知客户换单,避免影响时效 | V30: 46095 | W30: -
B31: 46094 | C31: 义乌 | D31: 浙江义乌稠江汇通路公司极电分部 | E31: 浙江义乌稠江汇通路公司极电分部JD5-T极电云仓五淘-J极电云仓五楼京-P极电云仓五拼-D极电云仓五楼抖-K极电云仓五楼快-X极电云仓5红622998221099 | F31: JD5-T极电云仓五淘-J极电云仓五楼京-P极电云仓五拼-D极电云仓五楼抖-K极电云仓五楼快-X极电云仓5红 | G31: 622998221099 | I31: =_xlfn.IFNA(_xlfn.XLOOKUP(_xlfn.XLOOKUP(D31,上榜过且清退过的网点!H:H,上榜过且清退过的网点!I:I),上榜过且清退过的网点!A:A,上榜过且清退过的网点!D:D),0) -> 1 | J31: 抖音 | K31: 1 | L31: 2403 | M31: 2400 | N31: 10.88% | O31: 2389 | P31: 7 | Q31: 5 | R31: 0.18% | S31: 5 | T31: 联系省区网管,未得到回复 | V31: - | W31: -
B32: 46094 | C32: 广西 | D32: 广西南宁青秀区凤岭公司崇铭服务部 | E32: 广西南宁青秀区凤岭公司崇铭服务部10013拼多多果幽生鲜甄选抖音三亩地农业甄选31305910013 | F32: 10013拼多多果幽生鲜甄选抖音三亩地农业甄选 | G32: 31305910013 | I32: =_xlfn.IFNA(_xlfn.XLOOKUP(_xlfn.XLOOKUP(D32,上榜过且清退过的网点!H:H,上榜过且清退过的网点!I:I),上榜过且清退过的网点!A:A,上榜过且清退过的网点!D:D),0) -> 0 | J32: 抖音 | K32: 1 | L32: 2250 | M32: 1914 | N32: 14.78% | O32: 1894 | P32: 0 | Q32: 0 | R32: 0 | S32: 0 | T32: 客户缺货,打包又 晚,导致当晚没有交件 | U32: 已安排人员协助打 包,后续会注意时效 | V32: 46096 | W32: -
B33: 46094 | C33: 湖北 | D33: 湖北潜江公司艾草分部 | E33: 湖北潜江公司艾草分部刘俊-梵悦VanJoy446790202501 | F33: 刘俊-梵悦VanJoy | G33: 446790202501 | H33: 是 | I33: =_xlfn.IFNA(_xlfn.XLOOKUP(_xlfn.XLOOKUP(D33,上榜过且清退过的网点!H:H,上榜过且清退过的网点!I:I),上榜过且清退过的网点!A:A,上榜过且清退过的网点!D:D),0) -> 1 | J33: 抖音 | K33: 3 | L33: 2026 | M33: 1902 | N33: 43.92% | O33: 0 | P33: 0 | Q33: 0 | R33: 0 | S33: 0 | T33: 商家缺货 | U33: 催促客户及时给货 | V33: 46096 | W33: -
B34: 46094 | C34: 海南 | D34: 海南东方市公司 | E34: 海南东方市公司执vKS570342662455 | F34: 执vKS | G34: 570342662455 | I34: =_xlfn.IFNA(_xlfn.XLOOKUP(_xlfn.XLOOKUP(D34,上榜过且清退过的网点!H:H,上榜过且清退过的网点!I:I),上榜过且清退过的网点!A:A,上榜过且清退过的网点!D:D),0) -> 0 | J34: 抖音 | K34: 3 | L34: 3273 | M34: 1624 | N34: 40.65% | O34: 1622 | P34: 0 | Q34: 0 | R34: 0 | S34: 0 | T34: 客户缺货 | U34: 已关闭批里揽收，目前是手动揽收，已告知超时之前做始发退回，不允许超时 | V34: 46094 | W34: -
B35: 46094 | C35: 贵州 | D35: 贵州遵义新仁怀市公司苍龙街道服务部 | E35: 贵州遵义新仁怀市公司苍龙街道服务部钰洁小卖部983759102326 | F35: 钰洁小卖部 | G35: 983759102326 | I35: =_xlfn.IFNA(_xlfn.XLOOKUP(_xlfn.XLOOKUP(D35,上榜过且清退过的网点!H:H,上榜过且清退过的网点!I:I),上榜过且清退过的网点!A:A,上榜过且清退过的网点!D:D),0) -> 0 | J35: 淘天 | K35: 1 | L35: 0 | M35: 0 | N35: 0 | O35: 0 | P35: 2800 | Q35: 2800 | R35: 50% | S35: 2800 | T35: 商家缺货 | U35: 通知商家改善，按时交件发出 | V35: 46096 | W35: -
B36: 46094 | C36: 贵州 | D36: 贵州贵阳观山湖世纪城公司 | E36: 贵州贵阳观山湖世纪城公司王孟利551515111111 | F36: 王孟利 | G36: 551515111111 | I36: =_xlfn.IFNA(_xlfn.XLOOKUP(_xlfn.XLOOKUP(D36,上榜过且清退过的网点!H:H,上榜过且清退过的网点!I:I),上榜过且清退过的网点!A:A,上榜过且清退过的网点!D:D),0) -> 0 | J36: 淘天 | K36: 2 | L36: 0 | M36: 0 | N36: 0 | O36: 0 | P36: 2088 | Q36: 2013 | R36: 96.36% | S36: 113 | T36: 商家缺货 | U36: 通知商家改善，按时交件发出 | V36: 46096 | W36: -
B37: 46094 | C37: 杭州 | D37: 浙江杭州萧山区新塘公司 | E37: 浙江杭州萧山区新塘公司红宝石分部-沐洛311420786786 | F37: 红宝石分部-沐洛 | G37: 311420786786 | H37: 是 | I37: =_xlfn.IFNA(_xlfn.XLOOKUP(_xlfn.XLOOKUP(D37,上榜过且清退过的网点!H:H,上榜过且清退过的网点!I:I),上榜过且清退过的网点!A:A,上榜过且清退过的网点!D:D),0) -> 0 | J37: 淘天 | K37: 7 | L37: 0 | M37: 0 | N37: 0 | O37: 0 | P37: 2158 | Q37: 1423 | R37: 15.14% | S37: 647 | T37: 客户缺货 | U37: 72H交不出做退回 | V37: - | W37: -
B38: 46094 | C38: 南京 | D38: 江苏南京浦口区新城公司 | E38: 江苏南京浦口区新城公司凤凰新华书店211149548426 | F38: 凤凰新华书店 | G38: 211149548426 | H38: 是 | I38: =_xlfn.IFNA(_xlfn.XLOOKUP(_xlfn.XLOOKUP(D38,上榜过且清退过的网点!H:H,上榜过且清退过的网点!I:I),上榜过且清退过的网点!A:A,上榜过且清退过的网点!D:D),0) -> 0 | J38: 淘天 | K38: 5 | L38: 4 | M38: 0 | N38: 0% | O38: 0 | P38: 1632 | Q38: 1149 | R38: 3.61% | S38: 881 | T38: 国营企业，9点之后一直在揽收又交不到分拨中心，考核一直有但是网点没改善 | U38: 省总对接拉群采取措施解决 | V38: - | W38: -
B39: 46094 | C39: 义乌 | D39: 浙江义乌稠江弘贸路公司 | E39: 浙江义乌稠江弘贸路公司美优baihuo355310100001 | F39: 美优baihuo | G39: 355310100001 | H39: 是 | I39: =_xlfn.IFNA(_xlfn.XLOOKUP(_xlfn.XLOOKUP(D39,上榜过且清退过的网点!H:H,上榜过且清退过的网点!I:I),上榜过且清退过的网点!A:A,上榜过且清退过的网点!D:D),0) -> 0 | J39: 淘天 | K39: 1 | L39: 0 | M39: 0 | N39: 0 | O39: 0 | P39: 1185 | Q39: 803 | R39: 0.59% | S39: 194 | T39: 联系省区网管,未得到回复 | V39: - | W39: -
B40: 46095 | C40: 北京 | D40: 河北韵达鑫通公司慕菲兰分部 | E40: 河北韵达鑫通公司慕菲兰分部妮雅依人服饰-张雷524818149441 | F40: 妮雅依人服饰-张雷 | G40: 524818149441 | I40: =_xlfn.IFNA(_xlfn.XLOOKUP(_xlfn.XLOOKUP(D40,上榜过且清退过的网点!H:H,上榜过且清退过的网点!I:I),上榜过且清退过的网点!A:A,上榜过且清退过的网点!D:D),0) -> 3 | J40: 抖音 | K40: 2 | L40: 4791 | M40: 4405 | N40: 25.62% | O40: 12 | P40: 0 | Q40: 0 | R40: 0 | S40: 0 | T40: 客户缺货,打包延迟,导致未及时交件 | U40: 已加班及时处理打包发出且做始发退回 | V40: 46096 | W40: -
B41: 46095 | C41: 广西 | D41: 广西南宁青秀区凤岭公司崇铭服务部 | E41: 广西南宁青秀区凤岭公司崇铭服务部芒果19淘宝cxxxxxxt京东Qq417092644拼多多曾似水果生鲜官方旗舰店抖音农夫果园甄选快手阿超在果园白马视频号蓓蕾家的日常生活3130596019 | F41: 芒果19淘宝cxxxxxxt京东Qq417092644拼多多曾似水果生鲜官方旗舰店抖音农夫果园甄选快手阿超在果园白马视频号蓓蕾家的日常生活 | G41: 3130596019 | H41: 是 | I41: =_xlfn.IFNA(_xlfn.XLOOKUP(_xlfn.XLOOKUP(D41,上榜过且清退过的网点!H:H,上榜过且清退过的网点!I:I),上榜过且清退过的网点!A:A,上榜过且清退过的网点!D:D),0) -> 0 | J41: 抖音 | K41: 1 | L41: 9535 | M41: 3920 | N41: 27.88% | O41: 2765 | P41: 0 | Q41: 0 | R41: 0 | S41: 0 | T41: 生鲜客户，缺货打包晚 | U41: 安排人员协助打 包,后续会注意时效 | V41: 46096 | W41: -
B42: 46095 | C42: 广佛中 | D42: 广东广州增城新塘白江村公司东洲服务部 | E42: 广东广州增城新塘白江村公司东洲服务部100812慕至尚服饰-李威客户459740100812 | F42: 100812慕至尚服饰-李威客户 | G42: 459740100812 | H42: 是 | I42: =_xlfn.IFNA(_xlfn.XLOOKUP(_xlfn.XLOOKUP(D42,上榜过且清退过的网点!H:H,上榜过且清退过的网点!I:I),上榜过且清退过的网点!A:A,上榜过且清退过的网点!D:D),0) -> 0 | J42: 抖音 | K42: 3 | L42: 3962 | M42: 3281 | N42: 26.3% | O42: 2312 | P42: 0 | Q42: 0 | R42: 0 | S42: 0 | T42: 服装客户缺货 | U42: 后续超时部分及时通 知客户换单,避免影响时效 | V42: 46095 | W42: -
B43: 46095 | C43: 广佛中 | D43: 广东中山富民公司阜沙卫民分部 | E43: 广东中山富民公司阜沙卫民分部真米生活电器旗舰店102068569899 | F43: 真米生活电器旗舰店 | G43: 102068569899 | I43: =_xlfn.IFNA(_xlfn.XLOOKUP(_xlfn.XLOOKUP(D43,上榜过且清退过的网点!H:H,上榜过且清退过的网点!I:I),上榜过且清退过的网点!A:A,上榜过且清退过的网点!D:D),0) -> 3 | J43: 抖音 | K43: 1 | L43: 5100 | M43: 2638 | N43: 42.39% | O43: 1026 | P43: 0 | Q43: 0 | R43: 0 | S43: 0 | T43: 客户缺货 | U43: 已经通知超时对接商家做始发退回 | V43: 46096 | W43: -
B44: 46095 | C44: 苏州 | D44: 江苏苏州常熟市招商城公司华联服务部 | E44: 江苏苏州常熟市招商城公司华联服务部聚福-蓝续服饰484398576648 | F44: 聚福-蓝续服饰 | G44: 484398576648 | H44: 是 | I44: =_xlfn.IFNA(_xlfn.XLOOKUP(_xlfn.XLOOKUP(D44,上榜过且清退过的网点!H:H,上榜过且清退过的网点!I:I),上榜过且清退过的网点!A:A,上榜过且清退过的网点!D:D),0) -> 0 | J44: 抖音 | K44: 3 | L44: 3629 | M44: 2327 | N44: 7.27% | O44: 120 | P44: 15 | Q44: 14 | R44: 9.59% | S44: 0 | T44: 服装客户缺货 | U44: 已解决 | V44: 46096 | W44: -
B45: 46095 | C45: 山西 | D45: 山西阳泉高新区公司 | E45: 山西阳泉高新区公司树直-善良-零食260085657658 | F45: 树直-善良-零食 | G45: 260085657658 | I45: =_xlfn.IFNA(_xlfn.XLOOKUP(_xlfn.XLOOKUP(D45,上榜过且清退过的网点!H:H,上榜过且清退过的网点!I:I),上榜过且清退过的网点!A:A,上榜过且清退过的网点!D:D),0) -> 0 | J45: 淘天 | K45: 1 | L45: 0 | M45: 0 | N45: 0 | O45: 0 | P45: 14999 | Q45: 14999 | R45: 99.99% | S45: 14999 | T45: 联系省区网管,未得到回复 | V45: - | W45: -
B46: 46095 | C46: 杭州 | D46: 浙江杭州萧山区新塘公司 | E46: 浙江杭州萧山区新塘公司红宝石分部-沐洛311420786786 | F46: 红宝石分部-沐洛 | G46: 311420786786 | H46: 是 | I46: =_xlfn.IFNA(_xlfn.XLOOKUP(_xlfn.XLOOKUP(D46,上榜过且清退过的网点!H:H,上榜过且清退过的网点!I:I),上榜过且清退过的网点!A:A,上榜过且清退过的网点!D:D),0) -> 0 | J46: 淘天 | K46: 7 | L46: 0 | M46: 0 | N46: 0 | O46: 0 | P46: 2479 | Q46: 1647 | R46: 17.03% | S46: 920 | T46: 客户缺货 | U46: 72H交不出做退回 | V46: - | W46: -
B47: 46095 | C47: 南京 | D47: 江苏南京浦口区新城公司 | E47: 江苏南京浦口区新城公司凤凰新华书店211149548426 | F47: 凤凰新华书店 | G47: 211149548426 | H47: 是 | I47: =_xlfn.IFNA(_xlfn.XLOOKUP(_xlfn.XLOOKUP(D47,上榜过且清退过的网点!H:H,上榜过且清退过的网点!I:I),上榜过且清退过的网点!A:A,上榜过且清退过的网点!D:D),0) -> 0 | J47: 淘天 | K47: 5 | L47: 0 | M47: 0 | N47: 0 | O47: 0 | P47: 1167 | Q47: 1155 | R47: 4.69% | S47: 871 | T47: 国营企业，9点之后一直在揽收又交不到分拨中心，考核一直有但是网点没改善 | U47: 省总对接拉群采取措施解决 | V47: - | W47: -
B48: 46095 | C48: 湖北 | D48: 湖北营销市场部 | E48: 湖北营销市场部好礼云仓392472329696 | F48: 好礼云仓 | G48: 392472329696 | H48: 是 | I48: =_xlfn.IFNA(_xlfn.XLOOKUP(_xlfn.XLOOKUP(D48,上榜过且清退过的网点!H:H,上榜过且清退过的网点!I:I),上榜过且清退过的网点!A:A,上榜过且清退过的网点!D:D),0) -> 0 | J48: 淘天 | K48: 2 | L48: 0 | M48: 0 | N48: 0 | O48: 0 | P48: 921 | Q48: 813 | R48: 6.81% | S48: 33 | T48: 分拨滞留 | U48: 已对接分拨操作，后续注意时效 | V48: 46096 | W48: -
B49: 46095 | C49: 安徽 | D49: 安徽肥东县龙岗镇公司龙岗分部 | E49: 安徽肥东县龙岗镇公司龙岗分部合丰农点赞883521963561 | F49: 合丰农点赞 | G49: 883521963561 | I49: =_xlfn.IFNA(_xlfn.XLOOKUP(_xlfn.XLOOKUP(D49,上榜过且清退过的网点!H:H,上榜过且清退过的网点!I:I),上榜过且清退过的网点!A:A,上榜过且清退过的网点!D:D),0) -> 0 | J49: 淘天 | K49: 1 | L49: 0 | M49: 0 | N49: 0 | O49: 0 | P49: 647 | Q49: 647 | R49: 97% | S49: 0 | T49: 农产品种子客户， 缺货 | U49: 已通知厂家增加人手生产 | V49: 46097 | W49: -
B50: 46096 | C50: 广佛中 | D50: 广东广州增城新塘白江村公司东洲服务部 | E50: 广东广州增城新塘白江村公司东洲服务部100812慕至尚服饰-李威客户459740100812 | F50: 100812慕至尚服饰-李威客户 | G50: 459740100812 | H50: 是 | I50: =_xlfn.IFNA(_xlfn.XLOOKUP(_xlfn.XLOOKUP(D50,上榜过且清退过的网点!H:H,上榜过且清退过的网点!I:I),上榜过且清退过的网点!A:A,上榜过且清退过的网点!D:D),0) -> 0 | J50: 抖音 | K50: 3 | L50: 6180 | M50: 5478 | N50: 43.05% | O50: 3584 | P50: 0 | Q50: 0 | R50: 0 | S50: 0 | T50: 服装客户缺货 | U50: 后续超时部分及时通 知客户换单,避免影响时效 | V50: 46095 | W50: -
B51: 46096 | C51: 北京 | D51: 河北韵达鑫通公司慕菲兰分部 | E51: 河北韵达鑫通公司慕菲兰分部妮雅依人服饰-张雷524818149441 | F51: 妮雅依人服饰-张雷 | G51: 524818149441 | I51: =_xlfn.IFNA(_xlfn.XLOOKUP(_xlfn.XLOOKUP(D51,上榜过且清退过的网点!H:H,上榜过且清退过的网点!I:I),上榜过且清退过的网点!A:A,上榜过且清退过的网点!D:D),0) -> 3 | J51: 抖音 | K51: 2 | L51: 3494 | M51: 2835 | N51: 32.38% | O51: 1033 | P51: 0 | Q51: 0 | R51: 0 | S51: 0 | T51: 客户缺货,打包延迟,导致未及时交件 | U51: 已加班及时处理打包发出且做始发退回 | V51: 46097 | W51: -
B52: 46096 | C52: 义乌 | D52: 浙江义乌稠江汇通路公司 | E52: 浙江义乌稠江汇通路公司通发----D龙欢的小店kkk3217642097 | F52: 通发----D龙欢的小店kkk | G52: 3217642097 | I52: =_xlfn.IFNA(_xlfn.XLOOKUP(_xlfn.XLOOKUP(D52,上榜过且清退过的网点!H:H,上榜过且清退过的网点!I:I),上榜过且清退过的网点!A:A,上榜过且清退过的网点!D:D),0) -> 1 | J52: 抖音 | K52: 1 | L52: 2531 | M52: 2476 | N52: 5.02% | O52: 2232 | P52: 0 | Q52: 0 | R52: 0 | S52: 0 | T52: 客户缺货 | U52: 未交出的做始发退回 | V52: 46097 | W52: -
B53: 46096 | C53: 湖北 | D53: 湖北天门市公司江汉便民寄存点分部 | E53: 湖北天门市公司江汉便民寄存点分部希姿轻奢女装-JH文涛-抖音637869810422 | F53: 希姿轻奢女装-JH文涛-抖音 | G53: 637869810422 | H53: 是 | I53: =_xlfn.IFNA(_xlfn.XLOOKUP(_xlfn.XLOOKUP(D53,上榜过且清退过的网点!H:H,上榜过且清退过的网点!I:I),上榜过且清退过的网点!A:A,上榜过且清退过的网点!D:D),0) -> 4 | J53: 抖音 | K53: 1 | L53: 3511 | M53: 2179 | N53: 55.97% | O53: 1742 | P53: 0 | Q53: 0 | R53: 0 | S53: 0 | T53: 联系省区网管,未得到回复 | V53: - | W53: -
B54: 46096 | C54: 苏州 | D54: 江苏苏州常熟市招商城公司华联服务部 | E54: 江苏苏州常熟市招商城公司华联服务部聚福-蓝续服饰484398576648 | F54: 聚福-蓝续服饰 | G54: 484398576648 | H54: 是 | I54: =_xlfn.IFNA(_xlfn.XLOOKUP(_xlfn.XLOOKUP(D54,上榜过且清退过的网点!H:H,上榜过且清退过的网点!I:I),上榜过且清退过的网点!A:A,上榜过且清退过的网点!D:D),0) -> 0 | J54: 抖音 | K54: 3 | L54: 2771 | M54: 1913 | N54: 7.61% | O54: 316 | P54: 7 | Q54: 4 | R54: 3.2% | S54: 0 | T54: 服装客户缺货 | U54: 已解决 | V54: 46097 | W54: -
B55: 46096 | C55: 贵州 | D55: 贵州镇宁县公司 | E55: 贵州镇宁县公司刷单罗勇561200560629 | F55: 刷单罗勇 | G55: 561200560629 | I55: =_xlfn.IFNA(_xlfn.XLOOKUP(_xlfn.XLOOKUP(D55,上榜过且清退过的网点!H:H,上榜过且清退过的网点!I:I),上榜过且清退过的网点!A:A,上榜过且清退过的网点!D:D),0) -> 0 | J55: 淘天 | K55: 1 | L55: 0 | M55: 0 | N55: 0 | O55: 0 | P55: 2299 | Q55: 2299 | R55: 100% | S55: 0 | T55: 客户缺货 | U55: 沟通客户缺货不要打出太多单 | V55: 46097 | W55: -
B56: 46096 | C56: 杭州 | D56: 浙江杭州萧山区新塘公司 | E56: 浙江杭州萧山区新塘公司红宝石分部-沐洛311420786786 | F56: 红宝石分部-沐洛 | G56: 311420786786 | H56: 是 | I56: =_xlfn.IFNA(_xlfn.XLOOKUP(_xlfn.XLOOKUP(D56,上榜过且清退过的网点!H:H,上榜过且清退过的网点!I:I),上榜过且清退过的网点!A:A,上榜过且清退过的网点!D:D),0) -> 0 | J56: 淘天 | K56: 7 | L56: 0 | M56: 0 | N56: 0 | O56: 0 | P56: 2338 | Q56: 1449 | R56: 14.61% | S56: 1141 | T56: 客户缺货 | U56: 72H交不出做退回,近期超时量在下降 | V56: - | W56: -
B57: 46096 | C57: 福建 | D57: 福建厦门岛外同安区新民公司 | E57: 福建厦门岛外同安区新民公司金牌橱柜351489917906 | F57: 金牌橱柜 | G57: 351489917906 | I57: =_xlfn.IFNA(_xlfn.XLOOKUP(_xlfn.XLOOKUP(D57,上榜过且清退过的网点!H:H,上榜过且清退过的网点!I:I),上榜过且清退过的网点!A:A,上榜过且清退过的网点!D:D),0) -> 0 | J57: 淘天 | K57: 1 | L57: 0 | M57: 0 | N57: 0 | O57: 0 | P57: 1000 | Q57: 1000 | R57: 100% | S57: 0 | T57: 货量大，缺货，导致操作不出来 | U57: 增加人员操作处理 | V57: 46097 | W57: -
B58: 46096 | C58: 湖北 | D58: 湖北营销市场部 | E58: 湖北营销市场部好礼云仓392472329696 | F58: 好礼云仓 | G58: 392472329696 | H58: 是 | I58: =_xlfn.IFNA(_xlfn.XLOOKUP(_xlfn.XLOOKUP(D58,上榜过且清退过的网点!H:H,上榜过且清退过的网点!I:I),上榜过且清退过的网点!A:A,上榜过且清退过的网点!D:D),0) -> 0 | J58: 淘天 | K58: 3 | L58: 0 | M58: 0 | N58: 0 | O58: 0 | P58: 1645 | Q58: 711 | R58: 7.47% | S58: 76 | T58: 分拨滞留 | U58: 已对接分拨操作，后续注意时效 | V58: 46096 | W58: -
B59: 46096 | C59: 云南 | D59: 云南昆明五华区小西门公司 | E59: 云南昆明五华区小西门公司嘉华食品-新650005778899 | F59: 嘉华食品-新 | G59: 650005778899 | I59: =_xlfn.IFNA(_xlfn.XLOOKUP(_xlfn.XLOOKUP(D59,上榜过且清退过的网点!H:H,上榜过且清退过的网点!I:I),上榜过且清退过的网点!A:A,上榜过且清退过的网点!D:D),0) -> 0 | J59: 淘天 | K59: 1 | L59: 1 | M59: 0 | N59: 0% | O59: 0 | P59: 694 | Q59: 691 | R59: 23.34% | S59: 691 | T59: 联系省区网管,未得到回复 | V59: - | W59: -
B60: 46097 | C60: 广佛中 | D60: 广东广州增城新塘白江村公司东洲服务部 | E60: 广东广州增城新塘白江村公司东洲服务部100811潮文汇服饰穿搭-李威客户459740100811 | F60: 100811潮文汇服饰穿搭-李威客户 | G60: 459740100811 | H60: 是 | I60: =_xlfn.IFNA(_xlfn.XLOOKUP(_xlfn.XLOOKUP(D60,上榜过且清退过的网点!H:H,上榜过且清退过的网点!I:I),上榜过且清退过的网点!A:A,上榜过且清退过的网点!D:D),0) -> 0 | J60: 抖音 | K60: 1 | L60: 5164 | M60: 4404 | N60: 0.4231 | O60: 3541 | P60: 0 | Q60: 0 | R60: 0 | S60: 0 | T60: 客户缺货，提前揽收 | U60: 限单30%，同步客户，今日起停止提前揽收 | V60: 46099 | W60: -
B61: 46097 | C61: 湖北 | D61: 湖北天门市公司江汉便民寄存点分部 | E61: 湖北天门市公司江汉便民寄存点分部希姿轻奢女装-JH文涛-抖音637869810422 | F61: 希姿轻奢女装-JH文涛-抖音 | G61: 637869810422 | H61: 是 | I61: =_xlfn.IFNA(_xlfn.XLOOKUP(_xlfn.XLOOKUP(D61,上榜过且清退过的网点!H:H,上榜过且清退过的网点!I:I),上榜过且清退过的网点!A:A,上榜过且清退过的网点!D:D),0) -> 4 | J61: 抖音 | K61: 2 | L61: 5234 | M61: 3359 | N61: 0.5127 | O61: 2924 | P61: 0 | Q61: 0 | R61: 0 | S61: 0 | T61: 联系省区网管,未得到回复 | V61: - | W61: -
B62: 46097 | C62: 新疆 | D62: 新疆哈密公司中山北路便民服务站分部 | E62: 新疆哈密公司中山北路便民服务站分部北亩772191899031 | F62: 北亩 | G62: 772191899031 | I62: =_xlfn.IFNA(_xlfn.XLOOKUP(_xlfn.XLOOKUP(D62,上榜过且清退过的网点!H:H,上榜过且清退过的网点!I:I),上榜过且清退过的网点!A:A,上榜过且清退过的网点!D:D),0) -> 0 | J62: 抖音 | K62: 1 | L62: 4531 | M62: 3299 | N62: 0.7159 | O62: 202 | P62: 4 | Q62: 4 | R62: 1 | S62: 0 | T62: 奶品客户，偏远地区发货 | U62: 已及时处理发运 | V62: 46099 | W62: -
B63: 46097 | C63: 广佛中 | D63: 广东广州花都区新雅公司美林分部 | E63: 广东广州花都区新雅公司美林分部P93-掌味鲜食品店-抖音-赵总826727100042 | F63: P93-掌味鲜食品店-抖音-赵总 | G63: 826727100042 | I63: =_xlfn.IFNA(_xlfn.XLOOKUP(_xlfn.XLOOKUP(D63,上榜过且清退过的网点!H:H,上榜过且清退过的网点!I:I),上榜过且清退过的网点!A:A,上榜过且清退过的网点!D:D),0) -> 2 | J63: 抖音 | K63: 1 | L63: 3664 | M63: 3021 | N63: 0 | O63: 667 | P63: 0 | Q63: 0 | R63: 0 | S63: 0 | T63: 缺货客户 | U63: 已发出；未发出做始发退回 | V63: 46100 | W63: -
B64: 46097 | C64: 北京 | D64: 河北韵达鑫通公司慕菲兰分部 | E64: 河北韵达鑫通公司慕菲兰分部妮雅依人服饰-张雷524818149441 | F64: 妮雅依人服饰-张雷 | G64: 524818149441 | I64: =_xlfn.IFNA(_xlfn.XLOOKUP(_xlfn.XLOOKUP(D64,上榜过且清退过的网点!H:H,上榜过且清退过的网点!I:I),上榜过且清退过的网点!A:A,上榜过且清退过的网点!D:D),0) -> 3 | J64: 抖音 | K64: 3 | L64: 3401 | M64: 2565 | N64: 0.2885 | O64: 5 | P64: 0 | Q64: 0 | R64: 0 | S64: 0 | T64: 服装缺货客户 | U64: 给予2天改善期，无改善关闭分单权限 | V64: 46100 | W64: -
B65: 46097 | C65: 杭州 | D65: 浙江杭州萧山区新塘公司 | E65: 浙江杭州萧山区新塘公司红宝石分部-沐洛311420786786 | F65: 红宝石分部-沐洛 | G65: 311420786786 | H65: 是 | I65: =_xlfn.IFNA(_xlfn.XLOOKUP(_xlfn.XLOOKUP(D65,上榜过且清退过的网点!H:H,上榜过且清退过的网点!I:I),上榜过且清退过的网点!A:A,上榜过且清退过的网点!D:D),0) -> 0 | J65: 淘天 | K65: 7 | L65: 0 | M65: 0 | N65: 0 | O65: 0 | P65: 2279 | Q65: 2071 | R65: 0.2029 | S65: 415 | T65: 客户缺货 | U65: 72H交不出做始发退回 | V65: - | W65: 持续上榜客，省区一直未解决
B66: 46097 | C66: 杭州 | D66: 浙江杭州智达山公司 | E66: 浙江杭州智达山公司惊蛰的6号小店-公司967336203782 | F66: 惊蛰的6号小店-公司 | G66: 967336203782 | I66: =_xlfn.IFNA(_xlfn.XLOOKUP(_xlfn.XLOOKUP(D66,上榜过且清退过的网点!H:H,上榜过且清退过的网点!I:I),上榜过且清退过的网点!A:A,上榜过且清退过的网点!D:D),0) -> 0 | J66: 淘天 | K66: 1 | L66: 0 | M66: 0 | N66: 0 | O66: 0 | P66: 2057 | Q66: 2011 | R66: 0.0477 | S66: 343 | T66: 始发集包，部分错集包导致超时 | U66: 已处理，后续加强集包环节管控 | V66: 46099 | W66: -
B67: 46097 | C67: 河南 | D67: 河南郑州二七区金星公司西广场分部 | E67: 河南郑州二七区金星公司西广场分部公司账户4500348012 | F67: 公司账户 | G67: 4500348012 | I67: =_xlfn.IFNA(_xlfn.XLOOKUP(_xlfn.XLOOKUP(D67,上榜过且清退过的网点!H:H,上榜过且清退过的网点!I:I),上榜过且清退过的网点!A:A,上榜过且清退过的网点!D:D),0) -> 0 | J67: 淘天 | K67: 1 | L67: 0 | M67: 0 | N67: 0 | O67: 0 | P67: 732 | Q67: 732 | R67: 0.4698 | S67: 671 | T67: 此客户为市内件客户，忘记做签收 | U67: 每日核查数据，确保及时签收 | V67: 46099 | W67: -
B68: 46097 | C68: 福建 | D68: 福建龙海市公司 | E68: 福建龙海市公司百草味363102977126 | F68: 百草味 | G68: 363102977126 | H68: 是 | I68: =_xlfn.IFNA(_xlfn.XLOOKUP(_xlfn.XLOOKUP(D68,上榜过且清退过的网点!H:H,上榜过且清退过的网点!I:I),上榜过且清退过的网点!A:A,上榜过且清退过的网点!D:D),0) -> 0 | J68: 淘天 | K68: 1 | L68: 2 | M68: 2 | N68: 0.0153 | O68: 0 | P68: 649 | Q68: 649 | R68: 0.2179 | S68: 0 | T68: 司机忘记揽收 | U68: 内部考核司机，杜绝再次发生 | V68: 46098 | W68: -
B69: 46097 | C69: 广佛中 | D69: 广东广州番禺南村公司锦江服务部 | E69: 广东广州番禺南村公司锦江服务部乐-舒琳美旗舰店-天猫101952951977 | F69: 乐-舒琳美旗舰店-天猫 | G69: 101952951977 | H69: 是 | I69: =_xlfn.IFNA(_xlfn.XLOOKUP(_xlfn.XLOOKUP(D69,上榜过且清退过的网点!H:H,上榜过且清退过的网点!I:I),上榜过且清退过的网点!A:A,上榜过且清退过的网点!D:D),0) -> 0 | J69: 淘天 | K69: 1 | L69: 0 | M69: 0 | N69: 0 | O69: 0 | P69: 728 | Q69: 597 | R69: 0.1182 | S69: 578 | T69: 联系省区网管,未得到回复 | V69: - | W69: -
B70: 46098 | C70: 广佛中 | D70: 广东广州花都区新雅公司美林分部 | E70: 广东广州花都区新雅公司美林分部P93-掌味鲜食品店-抖音-赵总826727100042 | F70: P93-掌味鲜食品店-抖音-赵总 | G70: 826727100042 | I70: =_xlfn.IFNA(_xlfn.XLOOKUP(_xlfn.XLOOKUP(D70,上榜过且清退过的网点!H:H,上榜过且清退过的网点!I:I),上榜过且清退过的网点!A:A,上榜过且清退过的网点!D:D),0) -> 2 | J70: 抖音 | K70: 2 | L70: 6302 | M70: 4368 | N70: 0 | O70: 1512 | P70: 0 | Q70: 0 | R70: 0 | S70: 0 | T70: 近期缺货客户 | U70: 36H交不出做始发退回 | V70: 46100 | W70: -
B71: 46098 | C71: 新疆 | D71: 新疆哈密公司中山北路便民服务站分部 | E71: 新疆哈密公司中山北路便民服务站分部北亩772191899031 | F71: 北亩 | G71: 772191899031 | I71: =_xlfn.IFNA(_xlfn.XLOOKUP(_xlfn.XLOOKUP(D71,上榜过且清退过的网点!H:H,上榜过且清退过的网点!I:I),上榜过且清退过的网点!A:A,上榜过且清退过的网点!D:D),0) -> 0 | J71: 抖音 | K71: 2 | L71: 4324 | M71: 4289 | N71: 0.9794 | O71: 1 | P71: 0 | Q71: 0 | R71: 0 | S71: 0 | T71: 奶品客户，偏远地区发货 | U71: 考核96H交件，已及时处理发运 | V71: 46100 | W71: -
B72: 46098 | C72: 广佛中 | D72: 广东广州增城新塘白江村公司东洲服务部 | E72: 广东广州增城新塘白江村公司东洲服务部100811潮文汇服饰穿搭-李威客户459740100811 | F72: 100811潮文汇服饰穿搭-李威客户 | G72: 459740100811 | H72: 是 | I72: =_xlfn.IFNA(_xlfn.XLOOKUP(_xlfn.XLOOKUP(D72,上榜过且清退过的网点!H:H,上榜过且清退过的网点!I:I),上榜过且清退过的网点!A:A,上榜过且清退过的网点!D:D),0) -> 0 | J72: 抖音 | K72: 2 | L72: 5159 | M72: 4057 | N72: 0.3487 | O72: 2917 | P72: 0 | Q72: 0 | R72: 0 | S72: 0 | T72: 严重缺货客户 | U72: 限单前一天30% | V72: 46103 | W72: -
B73: 46098 | C73: 湖北 | D73: 湖北天门市公司江汉便民寄存点分部 | E73: 湖北天门市公司江汉便民寄存点分部希姿轻奢女装-JH文涛-抖音637869810422 | F73: 希姿轻奢女装-JH文涛-抖音 | G73: 637869810422 | H73: 是 | I73: =_xlfn.IFNA(_xlfn.XLOOKUP(_xlfn.XLOOKUP(D73,上榜过且清退过的网点!H:H,上榜过且清退过的网点!I:I),上榜过且清退过的网点!A:A,上榜过且清退过的网点!D:D),0) -> 4 | J73: 抖音 | K73: 3 | L73: 5764 | M73: 3522 | N73: 0.5291 | O73: 3069 | P73: 0 | Q73: 0 | R73: 0 | S73: 0 | T73: 客户缺货，提前揽收 | U73: 催促客户及时交件 | V73: - | W73: -
B74: 46098 | C74: 湖北 | D74: 湖北天门市公司国投运营中心服务部 | E74: 湖北天门市公司国投运营中心服务部雨涵的衣橱-GT福多多-抖音430697230949 | F74: 雨涵的衣橱-GT福多多-抖音 | G74: 430697230949 | I74: =_xlfn.IFNA(_xlfn.XLOOKUP(_xlfn.XLOOKUP(D74,上榜过且清退过的网点!H:H,上榜过且清退过的网点!I:I),上榜过且清退过的网点!A:A,上榜过且清退过的网点!D:D),0) -> 0 | J74: 抖音 | K74: 0.7436 | L74: 3717 | M74: 3208 | N74: 0.7436 | O74: 2559 | P74: 0 | Q74: 0 | R74: 0 | S74: 0 | T74: 客户缺货，提前揽收 | U74: 催促客户及时交件 | V74: - | W74: -
B75: 46098 | C75: 安徽 | D75: 安徽安庆刘纪工业园公司 | E75: 安徽安庆刘纪工业园公司童装745099200110 | F75: 童装 | G75: 745099200110 | I75: =_xlfn.IFNA(_xlfn.XLOOKUP(_xlfn.XLOOKUP(D75,上榜过且清退过的网点!H:H,上榜过且清退过的网点!I:I),上榜过且清退过的网点!A:A,上榜过且清退过的网点!D:D),0) -> 0 | J75: 抖音 | K75: 0.7436 | L75: 2623 | M75: 2180 | N75: 0.7365 | O75: 2179 | P75: 0 | Q75: 0 | R75: 0 | S75: 0 | T75: 网点距离分拨较远,车子经常限速晚点；客户经常生产不出来 | U75: 该客户目前已停止合作 | V75: 46100 | W75: -
B76: 46098 | C76: 天津 | D76: 天津宝坻区新城公司 | E76: 天津宝坻区新城公司公司自营506045559913 | F76: 公司自营 | G76: 506045559913 | I76: =_xlfn.IFNA(_xlfn.XLOOKUP(_xlfn.XLOOKUP(D76,上榜过且清退过的网点!H:H,上榜过且清退过的网点!I:I),上榜过且清退过的网点!A:A,上榜过且清退过的网点!D:D),0) -> 0 | J76: 淘天 | K76: 1 | L76: 0 | M76: 0 | N76: 0 | O76: 0 | P76: 1076 | Q76: 1076 | R76: 1 | S76: 1076 | T76: 同城电子单，忘记做签收 | U76: 通知网点同城件改为多多平台 | V76: 46100 | W76: -
B77: 46098 | C77: 深莞惠 | D77: 广东东莞KH公司樟木头服务部 | E77: 广东东莞KH公司樟木头服务部tb7850124150-淘宝-公司316932100290 | F77: tb7850124150-淘宝-公司 | G77: 316932100290 | I77: =_xlfn.IFNA(_xlfn.XLOOKUP(_xlfn.XLOOKUP(D77,上榜过且清退过的网点!H:H,上榜过且清退过的网点!I:I),上榜过且清退过的网点!A:A,上榜过且清退过的网点!D:D),0) -> 0 | J77: 淘天 | K77: 1 | L77: 0 | M77: 0 | N77: 0 | O77: 0 | P77: 1446 | Q77: 893 | R77: 0.5953 | S77: 1 | T77: 自揽自签的同城件 | U77: 已解决 | V77: 46099 | W77: -
B78: 46098 | C78: 山东 | D78: 山东临沂罗庄区双月公司 | E78: 山东临沂罗庄区双月公司王成-花之冠多肉-淘宝905606122989 | F78: 王成-花之冠多肉-淘宝 | G78: 905606122989 | I78: =_xlfn.IFNA(_xlfn.XLOOKUP(_xlfn.XLOOKUP(D78,上榜过且清退过的网点!H:H,上榜过且清退过的网点!I:I),上榜过且清退过的网点!A:A,上榜过且清退过的网点!D:D),0) -> 0 | J78: 淘天 | K78: 1 | L78: 0 | M78: 0 | N78: 0 | O78: 0 | P78: 840 | Q78: 781 | R78: 0.3724 | S78: 776 | T78: 客户缺货提前揽收，未告知网点 | U78: 沟通客户不要提前下订单，实物揽收 | V78: 46099 | W78: -
B79: 46098 | C79: 杭州 | D79: 浙江杭州萧山区新塘公司 | E79: 浙江杭州萧山区新塘公司红宝石分部-沐洛311420786786 | F79: 红宝石分部-沐洛 | G79: 311420786786 | H79: 是 | I79: =_xlfn.IFNA(_xlfn.XLOOKUP(_xlfn.XLOOKUP(D79,上榜过且清退过的网点!H:H,上榜过且清退过的网点!I:I),上榜过且清退过的网点!A:A,上榜过且清退过的网点!D:D),0) -> 0 | J79: 淘天 | K79: 7 | L79: 0 | M79: 0 | N79: 0 | O79: 0 | P79: 1229 | Q79: 764 | R79: 0.0961 | S79: 50 | T79: 客户缺货 | U79: 72H交不出做始发退回 | V79: - | W79: -
B80: 46099 | C80: 广佛中 | D80: 广东广州增城新塘白江村公司东洲服务部 | E80: 广东广州增城新塘白江村公司东洲服务部100811潮文汇服饰穿搭-李威客户459740100811 | F80: 100811潮文汇服饰穿搭-李威客户 | G80: 459740100811 | I80: =_xlfn.IFNA(_xlfn.XLOOKUP(_xlfn.XLOOKUP(D80,上榜过且清退过的网点!H:H,上榜过且清退过的网点!I:I),上榜过且清退过的网点!A:A,上榜过且清退过的网点!D:D),0) -> 0 | J80: 抖音 | K80: 3 | L80: 5695 | M80: 4733 | N80: 0.4002 | O80: 2547 | P80: 0 | Q80: 0 | R80: 0 | S80: 0 | T80: 严重缺货客户 | U80: 已采取限单30%措施，无改善将停止揽收 | V80: 46103 | W80: -
B81: 46099 | C81: 深莞惠 | D81: 广东深圳KH公司福永盛和兴分部 | E81: 广东深圳KH公司福永盛和兴分部绯红女装供应链4店518777279019 | F81: 绯红女装供应链4店 | G81: 518777279019 | I81: =_xlfn.IFNA(_xlfn.XLOOKUP(_xlfn.XLOOKUP(D81,上榜过且清退过的网点!H:H,上榜过且清退过的网点!I:I),上榜过且清退过的网点!A:A,上榜过且清退过的网点!D:D),0) -> 3 | J81: 抖音 | K81: 1 | L81: 2802 | M81: 2456 | N81: 0.1095 | O81: 1818 | P81: 0 | Q81: 0 | R81: 0 | S81: 0 | T81: 服装缺货客户 | U81: 省内会议网管跟反馈跟进解决 | V81: 46103 | W81: -
B82: 46099 | C82: 江西 | D82: 江西新余渝水公司万商红服务部 | E82: 江西新余渝水公司万商红服务部乔卡瑞女鞋130419918888 | F82: 乔卡瑞女鞋 | G82: 130419918888 | I82: =_xlfn.IFNA(_xlfn.XLOOKUP(_xlfn.XLOOKUP(D82,上榜过且清退过的网点!H:H,上榜过且清退过的网点!I:I),上榜过且清退过的网点!A:A,上榜过且清退过的网点!D:D),0) -> 0 | J82: 抖音 | K82: 2 | L82: 2095 | M82: 2085 | N82: 1 | O82: 0 | P82: 1 | Q82: 0 | R82: 0 | S82: 0 | T82: 客户扫描设备故障导致当天订单未发 | U82: 已经解决 | V82: 46100 | W82: -
B83: 46099 | C83: 湖北 | D83: 湖北天门市公司江汉便民寄存点分部 | E83: 湖北天门市公司江汉便民寄存点分部希姿轻奢女装-JH文涛-抖音637869810422 | F83: 希姿轻奢女装-JH文涛-抖音 | G83: 637869810422 | I83: =_xlfn.IFNA(_xlfn.XLOOKUP(_xlfn.XLOOKUP(D83,上榜过且清退过的网点!H:H,上榜过且清退过的网点!I:I),上榜过且清退过的网点!A:A,上榜过且清退过的网点!D:D),0) -> 4 | J83: 抖音 | K83: 4 | L83: 3384 | M83: 2005 | N83: 0.5133 | O83: 1648 | P83: 0 | Q83: 0 | R83: 0 | S83: 0 | T83: 自产服装客户，布料问题导致严重缺货 | U83: 催促客户及时交件，预计三天左右解决 | V83: 46103 | W83: -
B84: 46099 | C84: 深莞惠 | D84: 广东深圳KH公司福永盛和兴分部 | E84: 广东深圳KH公司福永盛和兴分部针织二哥518777279021 | F84: 针织二哥 | G84: 518777279021 | I84: =_xlfn.IFNA(_xlfn.XLOOKUP(_xlfn.XLOOKUP(D84,上榜过且清退过的网点!H:H,上榜过且清退过的网点!I:I),上榜过且清退过的网点!A:A,上榜过且清退过的网点!D:D),0) -> 3 | J84: 抖音 | K84: 1 | L84: 1808 | M84: 1719 | N84: 0.8472 | O84: 855 | P84: 0 | Q84: 0 | R84: 0 | S84: 0 | T84: 服装缺货客户 | U84: 省内会议网管跟反馈跟进解决 | V84: 46101 | W84: -
B85: 46099 | C85: 河南 | D85: 河南荥阳市公司 | E85: 河南荥阳市公司可爱佳童装450042240210 | F85: 可爱佳童装 | G85: 450042240210 | I85: =_xlfn.IFNA(_xlfn.XLOOKUP(_xlfn.XLOOKUP(D85,上榜过且清退过的网点!H:H,上榜过且清退过的网点!I:I),上榜过且清退过的网点!A:A,上榜过且清退过的网点!D:D),0) -> 0 | J85: 淘天 | K85: 1 | L85: 0 | M85: 0 | N85: 0 | O85: 0 | P85: 9000 | Q85: 3788 | R85: 0.3788 | S85: 3788 | T85: 此客户为市内件客户，忘记做签收 | U85: 已经解决 | V85: 46100 | W85: -
B86: 46099 | C86: 杭州 | D86: 浙江杭州萧山区新塘公司 | E86: 浙江杭州萧山区新塘公司红宝石分部-沐洛311420786786 | F86: 红宝石分部-沐洛 | G86: 311420786786 | H86: 是 | I86: =_xlfn.IFNA(_xlfn.XLOOKUP(_xlfn.XLOOKUP(D86,上榜过且清退过的网点!H:H,上榜过且清退过的网点!I:I),上榜过且清退过的网点!A:A,上榜过且清退过的网点!D:D),0) -> 0 | J86: 淘天 | K86: 7 | L86: 0 | M86: 0 | N86: 0 | O86: 0 | P86: 1843 | Q86: 1370 | R86: 0.1418 | S86: 494 | T86: 客户缺货 | U86: 72H交不出做始发退回 | V86: - | W86: -
B87: 46099 | C87: 云南 | D87: 云南剑川县公司 | E87: 云南剑川县公司寸国柱6713006267 | F87: 寸国柱 | G87: 6713006267 | I87: =_xlfn.IFNA(_xlfn.XLOOKUP(_xlfn.XLOOKUP(D87,上榜过且清退过的网点!H:H,上榜过且清退过的网点!I:I),上榜过且清退过的网点!A:A,上榜过且清退过的网点!D:D),0) -> 0 | J87: 淘天 | K87: 1 | L87: 0 | M87: 0 | N87: 0 | O87: 0 | P87: 1107 | Q87: 1107 | R87: 0.9964 | S87: 1107 | T87: 商家打错单 | U87: 这批单子全部拦截退回处理，已沟通网点先暂停商家出单，调整好在出单 | V87: 46101 | W87: -
B88: 46099 | C88: 广佛中 | D88: 广东广州番禺南村公司锦江服务部 | E88: 广东广州番禺南村公司锦江服务部乐-unifittoo服饰旗舰店101952951982 | F88: 乐-unifittoo服饰旗舰店 | G88: 101952951982 | I88: =_xlfn.IFNA(_xlfn.XLOOKUP(_xlfn.XLOOKUP(D88,上榜过且清退过的网点!H:H,上榜过且清退过的网点!I:I),上榜过且清退过的网点!A:A,上榜过且清退过的网点!D:D),0) -> 0 | J88: 淘天 | K88: 1 | L88: 0 | M88: 0 | N88: 0 | O88: 0 | P88: 1191 | Q88: 1031 | R88: 0.1933 | S88: 611 | T88: 服装缺货客户 | U88: 省内会议网管跟反馈跟进解决 | V88: 46101 | W88: -
B89: 46099 | C89: 云南 | D89: 云南昆明官渡区金马路公司 | E89: 云南昆明官渡区金马路公司宜优选水果旗舰店-丁650679650661 | F89: 宜优选水果旗舰店-丁 | G89: 650679650661 | I89: =_xlfn.IFNA(_xlfn.XLOOKUP(_xlfn.XLOOKUP(D89,上榜过且清退过的网点!H:H,上榜过且清退过的网点!I:I),上榜过且清退过的网点!A:A,上榜过且清退过的网点!D:D),0) -> 0 | J89: 淘天 | K89: 1 | L89: 0 | M89: 0 | N89: 0 | O89: 0 | P89: 809 | Q89: 808 | R89: 0.2092 | S89: 0 | T89: 水果客户，因天气降温水果品质未达标，导致采摘少，当天交件缺货 | U89: 延迟一天已经全部交件 | V89: 46100 | W89: -
B90: 46100 | C90: 广佛中 | D90: 广东广州花都区新雅公司 | E90: 广东广州花都区新雅公司P93-掌味鲜食品店-抖音-赵总826727100042 | F90: P93-掌味鲜食品店-抖音-赵总 | G90: 826727100042 | I90: =_xlfn.IFNA(_xlfn.XLOOKUP(_xlfn.XLOOKUP(D90,上榜过且清退过的网点!H:H,上榜过且清退过的网点!I:I),上榜过且清退过的网点!A:A,上榜过且清退过的网点!D:D),0) -> 2 | J90: 抖音 | K90: 3 | L90: 6908 | M90: 5468 | N90: 0.1546 | O90: 724 | P90: 0 | Q90: 0 | R90: 0 | S90: 0 | T90: 近期缺货客户 | U90: 36H交不出做始发退回 | V90: 46103 | W90: -
B91: 46100 | C91: 上海 | D91: 江苏昆山合丰公司 | E91: 江苏昆山合丰公司妞妞甄选女装横扇463163110057 | F91: 妞妞甄选女装横扇 | G91: 463163110057 | I91: =_xlfn.IFNA(_xlfn.XLOOKUP(_xlfn.XLOOKUP(D91,上榜过且清退过的网点!H:H,上榜过且清退过的网点!I:I),上榜过且清退过的网点!A:A,上榜过且清退过的网点!D:D),0) -> 0 | J91: 抖音 | K91: 1 | L91: 3634 | M91: 2801 | N91: 0.4022 | O91: 191 | P91: 0 | Q91: 0 | R91: 0 | S91: 0 | T91: 客户缺一部分货，导致无法第一时间交件 | U91: 今日内解决，始发退回 | V91: 46102 | W91: -
B92: 46100 | C92: 揭阳 | D92: 广东揭西县公司永安分部 | E92: 广东揭西县公司永安分部叶蓝北话你知供应链抖李鹏彬522658802030 | F92: 叶蓝北话你知供应链抖李鹏彬 | G92: 522658802030 | I92: =_xlfn.IFNA(_xlfn.XLOOKUP(_xlfn.XLOOKUP(D92,上榜过且清退过的网点!H:H,上榜过且清退过的网点!I:I),上榜过且清退过的网点!A:A,上榜过且清退过的网点!D:D),0) -> 1 | J92: 抖音 | K92: 1 | L92: 2401 | M92: 2352 | N92: 0.9322 | O92: 0 | P92: 0 | Q92: 0 | R92: 0 | S92: 0 | T92: 联系省区网管,未得到回复 | V92: - | W92: -
B93: 46100 | C93: 福建 | D93: 福建石狮市公司抖音KH分部 | E93: 福建石狮市公司抖音KH分部永红-黄永红-千人慧优品服饰362551900800 | F93: 永红-黄永红-千人慧优品服饰 | G93: 362551900800 | I93: =_xlfn.IFNA(_xlfn.XLOOKUP(_xlfn.XLOOKUP(D93,上榜过且清退过的网点!H:H,上榜过且清退过的网点!I:I),上榜过且清退过的网点!A:A,上榜过且清退过的网点!D:D),0) -> 4 | J93: 抖音 | K93: 1 | L93: 2382 | M93: 2278 | N93: 0.4781 | O93: 258 | P93: 0 | Q93: 0 | R93: 0 | S93: 0 | T93: 新客户做了兜底揽收 | U93: 网点承诺三天内调整正常 | V93: 46104 | W93: -
B94: 46100 | C94: 苏州 | D94: 江苏苏州常熟莫城公司莫城街道服务部 | E94: 江苏苏州常熟莫城公司莫城街道服务部衣雅优选-陈浩938977200011 | F94: 衣雅优选-陈浩 | G94: 938977200011 | H94: 是 | I94: =_xlfn.IFNA(_xlfn.XLOOKUP(_xlfn.XLOOKUP(D94,上榜过且清退过的网点!H:H,上榜过且清退过的网点!I:I),上榜过且清退过的网点!A:A,上榜过且清退过的网点!D:D),0) -> 0 | J94: 抖音 | K94: 1 | L94: 3476 | M94: 2033 | N94: 0.1936 | O94: 320 | P94: 0 | Q94: 0 | R94: 0 | S94: 0 | T94: 客户缺货导致 | U94: 已经解决，有20票左右兜底始发退回 | V94: 46101 | W94: -
B95: 46100 | C95: 山西 | D95: 山西灵丘县公司 | E95: 山西灵丘县公司中源体育937300334126 | F95: 中源体育 | G95: 937300334126 | I95: =_xlfn.IFNA(_xlfn.XLOOKUP(_xlfn.XLOOKUP(D95,上榜过且清退过的网点!H:H,上榜过且清退过的网点!I:I),上榜过且清退过的网点!A:A,上榜过且清退过的网点!D:D),0) -> 0 | J95: 淘天 | K95: 1 | L95: 0 | M95: 0 | N95: 0 | O95: 0 | P95: 2977 | Q95: 2977 | R95: 1 | S95: 2508 | T95: 客户产品有问题，不能发了 | U95: 已通知网点做始发退回解决超时单量 | V95: 46102 | W95: -
B96: 46100 | C96: 杭州 | D96: 浙江杭州萧山区新塘公司 | E96: 浙江杭州萧山区新塘公司红宝石分部-沐洛311420786786 | F96: 红宝石分部-沐洛 | G96: 311420786786 | H96: 是 | I96: =_xlfn.IFNA(_xlfn.XLOOKUP(_xlfn.XLOOKUP(D96,上榜过且清退过的网点!H:H,上榜过且清退过的网点!I:I),上榜过且清退过的网点!A:A,上榜过且清退过的网点!D:D),0) -> 0 | J96: 淘天 | K96: 7 | L96: 0 | M96: 0 | N96: 0 | O96: 0 | P96: 2328 | Q96: 1819 | R96: 0.1847 | S96: 657 | T96: 客户缺货 | U96: 72H交不出做始发退回 | V96: - | W96: -
B97: 46100 | C97: 南京 | D97: 江苏连云港东海县公司 | E97: 江苏连云港东海县公司颜文静小石头珠宝222008996610 | F97: 颜文静小石头珠宝 | G97: 222008996610 | I97: =_xlfn.IFNA(_xlfn.XLOOKUP(_xlfn.XLOOKUP(D97,上榜过且清退过的网点!H:H,上榜过且清退过的网点!I:I),上榜过且清退过的网点!A:A,上榜过且清退过的网点!D:D),0) -> 0 | J97: 淘天 | K97: 1 | L97: 0 | M97: 0 | N97: 0 | O97: 0 | P97: 1590 | Q97: 1581 | R97: 0.5845 | S97: 0 | T97: 联系省区网管,未得到回复 | V97: - | W97: -
B98: 46100 | C98: 河北 | D98: 河北清河县公司清河服务部 | E98: 河北清河县公司清河服务部kogana88-裴志林-822790211444883013 | F98: kogana88-裴志林-822790 | G98: 211444883013 | I98: =_xlfn.IFNA(_xlfn.XLOOKUP(_xlfn.XLOOKUP(D98,上榜过且清退过的网点!H:H,上榜过且清退过的网点!I:I),上榜过且清退过的网点!A:A,上榜过且清退过的网点!D:D),0) -> 0 | J98: 淘天 | K98: 1 | L98: 0 | M98: 0 | N98: 0 | O98: 0 | P98: 1522 | Q98: 960 | R98: 0.1298 | S98: 0 | T98: 服装客户缺货 | U98: 已经解决 | V98: 46101 | W98: -
B99: 46100 | C99: 广佛中 | D99: 广东广州番禺南村公司锦江服务部 | E99: 广东广州番禺南村公司锦江服务部乐-unifittoo服饰旗舰店101952951982 | F99: 乐-unifittoo服饰旗舰店 | G99: 101952951982 | I99: =_xlfn.IFNA(_xlfn.XLOOKUP(_xlfn.XLOOKUP(D99,上榜过且清退过的网点!H:H,上榜过且清退过的网点!I:I),上榜过且清退过的网点!A:A,上榜过且清退过的网点!D:D),0) -> 0 | J99: 淘天 | K99: 2 | L99: 0 | M99: 0 | N99: 0 | O99: 0 | P99: 804 | Q99: 743 | R99: 0.1663 | S99: 358 | T99: 服装缺货客户 | U99: 省内会议网管跟反馈跟进解决 | V99: 46101 | W99: -
B100: 46101 | C100: 广佛中 | D100: 广东广州花都区新雅公司豪利分部 | E100: 广东广州花都区新雅公司豪利分部P93-食味鲜品店-抖音-赵总197415100001 | F100: P93-食味鲜品店-抖音-赵总 | G100: 197415100001 | I100: =_xlfn.IFNA(_xlfn.XLOOKUP(_xlfn.XLOOKUP(D100,上榜过且清退过的网点!H:H,上榜过且清退过的网点!I:I),上榜过且清退过的网点!A:A,上榜过且清退过的网点!D:D),0) -> 2 | J100: 抖音 | K100: 1 | L100: 4959 | M100: 3148 | N100: 0% | O100: 724 | P100: 0 | Q100: 0 | R100: 0 | S100: 0 | T100: 服装缺货客户 | U100: 已及时发出处理，超时部分做始发退回 | V100: 46104 | W100: -
B101: 46101 | C101: 深莞惠 | D101: 广东深圳KH公司福海露分部 | E101: 广东深圳KH公司福海露分部施瑶女装供应链518739279540 | F101: 施瑶女装供应链 | G101: 518739279540 | I101: =_xlfn.IFNA(_xlfn.XLOOKUP(_xlfn.XLOOKUP(D101,上榜过且清退过的网点!H:H,上榜过且清退过的网点!I:I),上榜过且清退过的网点!A:A,上榜过且清退过的网点!D:D),0) -> 3 | J101: 抖音 | K101: 1 | L101: 1432 | M101: 1430 | N101: 75.46% | O101: 951 | P101: 0 | Q101: 0 | R101: 0 | S101: 0 | T101: 缺货 | U101: 已对接商家发出，始发退回兜底 | V101: 46104 | W101: -
...

Sheet 近7天累计TOP客户
A1: 日期 | B1: 省 | C1: 分部名称 | D1: 唯一值（分部名称+客户名称+客户编码 | E1: 客户名称 | F1: 客户编码 | G1: 揽收-发运超时 | O1: 平台区分
G2: 抖音平台 | K2: 淘天平台
G3: 超24h | H3: 超36h | J3: 超48h | K3: 超24h | L3: 超36h | N3: 超48h
G4: 票件量 | H4: 单量 | I4: 超时率 | J4: 票件量 | K4: 票件量 | L4: 单量 | M4: 超时率 | N4: 票件量
A5: 46221 | B5: 广佛中 | C5: 广东佛山南海新河村公司 | D5: 广东佛山南海新河村公司公司直营-曼馨抖音珠茉美妆-启能拼多多大赚顺-启能菜鸟tb4336332592572014411986 | E5: 公司直营-曼馨抖音珠茉美妆-启能拼多多大赚顺-启能菜鸟tb4336332592 | F5: 572014411986 | G5: 2333 | H5: 1960 | I5: 25.42% | J5: 86 | K5: 0 | L5: 0 | M5: 0 | N5: 0 | O5: 抖音 | P5: =_xlfn.XLOOKUP(D5,TOP客户累计改善清单!E:E,TOP客户累计改善清单!K:K) -> 2 | Q5: =IF(O5="抖音",H5,L5) -> 1960 | R5: =IF(O5="抖音",ROUND(I5*100,2),ROUND(M5*100,2)) -> 25.42 | S5: =C5&"・"&E5&"【"&Q5&"票"&","&R5&"%"&"】"&P5&"次" -> 广东佛山南海新河村公司・公司直营-曼馨抖音珠茉美妆-启能拼多多大赚顺-启能菜鸟tb4336332592【1960票,25.42%】2次
A6: 46221 | B6: 苏州 | C6: 江苏苏州常熟市招商城公司 | D6: 江苏苏州常熟市招商城公司聚福-小灰兔681709798994 | E6: 聚福-小灰兔 | F6: 681709798994 | G6: 5014 | H6: 1845 | I6: 3.99% | J6: 12 | K6: 0 | L6: 0 | M6: 0 | N6: 0 | O6: 抖音 | P6: =_xlfn.XLOOKUP(D6,TOP客户累计改善清单!E:E,TOP客户累计改善清单!K:K) -> 1 | Q6: =IF(O6="抖音",H6,L6) -> 1845 | R6: =IF(O6="抖音",ROUND(I6*100,2),ROUND(M6*100,2)) -> 3.99 | S6: =C6&"・"&E6&"【"&Q6&"票"&","&R6&"%"&"】"&P6&"次" -> 江苏苏州常熟市招商城公司・聚福-小灰兔【1845票,3.99%】1次
A7: 46221 | B7: 河北 | C7: 河北南宫市公司 | D7: 河北南宫市公司胜利大街惠-岳世辉-快手追风潮童-抖音光伟童装工厂店-拼多多左左右右童-视频号小可爱童装-淘宝贵泽童装工厂951800650006 | E7: 胜利大街惠-岳世辉-快手追风潮童-抖音光伟童装工厂店-拼多多左左右右童-视频号小可爱童装-淘宝贵泽童装工厂 | F7: 951800650006 | G7: 1990 | H7: 1585 | I7: 26.84% | J7: 193 | K7: 0 | L7: 0 | M7: 0 | N7: 0 | O7: 抖音 | P7: =_xlfn.XLOOKUP(D7,TOP客户累计改善清单!E:E,TOP客户累计改善清单!K:K) -> 2 | Q7: =IF(O7="抖音",H7,L7) -> 1585 | R7: =IF(O7="抖音",ROUND(I7*100,2),ROUND(M7*100,2)) -> 26.84 | S7: =C7&"・"&E7&"【"&Q7&"票"&","&R7&"%"&"】"&P7&"次" -> 河北南宫市公司・胜利大街惠-岳世辉-快手追风潮童-抖音光伟童装工厂店-拼多多左左右右童-视频号小可爱童装-淘宝贵泽童装工厂【1585票,26.84%】2次
A8: 46221 | B8: 深莞惠 | C8: 广东深圳KH公司孟洁分部 | D8: 广东深圳KH公司孟洁分部溪南园829902455147 | E8: 溪南园 | F8: 829902455147 | G8: 2524 | H8: 1335 | I8: 10.48% | J8: 600 | K8: 0 | L8: 0 | M8: 0 | N8: 0 | O8: 抖音 | P8: =_xlfn.XLOOKUP(D8,TOP客户累计改善清单!E:E,TOP客户累计改善清单!K:K) -> 1 | Q8: =IF(O8="抖音",H8,L8) -> 1335 | R8: =IF(O8="抖音",ROUND(I8*100,2),ROUND(M8*100,2)) -> 10.48 | S8: =C8&"・"&E8&"【"&Q8&"票"&","&R8&"%"&"】"&P8&"次" -> 广东深圳KH公司孟洁分部・溪南园【1335票,10.48%】1次
A9: 46221 | B9: 安徽 | C9: 安徽亳州谯城道东公司 | D9: 安徽亳州谯城道东公司卢宏杰云仓T袅店K袅烟阁P燃叫冲饮旗舰店S袅烟阁慈行D燃叫咖啡582367513148 | E9: 卢宏杰云仓T袅店K袅烟阁P燃叫冲饮旗舰店S袅烟阁慈行D燃叫咖啡 | F9: 582367513148 | G9: 2141 | H9: 1228 | I9: 32.36% | J9: 3 | K9: 0 | L9: 0 | M9: 0 | N9: 0 | O9: 抖音 | P9: =_xlfn.XLOOKUP(D9,TOP客户累计改善清单!E:E,TOP客户累计改善清单!K:K) -> 1 | Q9: =IF(O9="抖音",H9,L9) -> 1228 | R9: =IF(O9="抖音",ROUND(I9*100,2),ROUND(M9*100,2)) -> 32.36 | S9: =C9&"・"&E9&"【"&Q9&"票"&","&R9&"%"&"】"&P9&"次" -> 安徽亳州谯城道东公司・卢宏杰云仓T袅店K袅烟阁P燃叫冲饮旗舰店S袅烟阁慈行D燃叫咖啡【1228票,32.36%】1次
A10: 46221 | B10: 深莞惠 | C10: 广东深圳公司锌东经KH分部 | D10: 广东深圳公司锌东经KH分部李圳-菜鸟-驰界贸易518066666666 | E10: 李圳-菜鸟-驰界贸易 | F10: 518066666666 | G10: 0 | H10: 0 | I10: 0 | J10: 0 | K10: 995 | L10: 822 | M10: 18.75% | N10: 0 | O10: 淘天 | P10: =_xlfn.XLOOKUP(D10,TOP客户累计改善清单!E:E,TOP客户累计改善清单!K:K) -> 1 | Q10: =IF(O10="抖音",H10,L10) -> 822 | R10: =IF(O10="抖音",ROUND(I10*100,2),ROUND(M10*100,2)) -> 18.75 | S10: =C10&"・"&E10&"【"&Q10&"票"&","&R10&"%"&"】"&P10&"次" -> 广东深圳公司锌东经KH分部・李圳-菜鸟-驰界贸易【822票,18.75%】1次
A11: 46221 | B11: 湖北 | C11: 湖北营销市场部 | D11: 湖北营销市场部好礼云仓392472329696 | E11: 好礼云仓 | F11: 392472329696 | G11: 0 | H11: 0 | I11: 0 | J11: 0 | K11: 1564 | L11: 521 | M11: 4.48% | N11: 8 | O11: 淘天 | P11: =_xlfn.XLOOKUP(D11,TOP客户累计改善清单!E:E,TOP客户累计改善清单!K:K) -> 1 | Q11: =IF(O11="抖音",H11,L11) -> 521 | R11: =IF(O11="抖音",ROUND(I11*100,2),ROUND(M11*100,2)) -> 4.48 | S11: =C11&"・"&E11&"【"&Q11&"票"&","&R11&"%"&"】"&P11&"次" -> 湖北营销市场部・好礼云仓【521票,4.48%】1次
A12: 46221 | B12: 安徽 | C12: 安徽合肥凤麟路公司 | D12: 安徽合肥凤麟路公司品越供应链225317100063 | E12: 品越供应链 | F12: 225317100063 | G12: 99 | H12: 44 | I12: 0.14% | J12: 21 | K12: 450 | L12: 423 | M12: 3.44% | N12: 11 | O12: 淘天 | P12: =_xlfn.XLOOKUP(D12,TOP客户累计改善清单!E:E,TOP客户累计改善清单!K:K) -> 1 | Q12: =IF(O12="抖音",H12,L12) -> 423 | R12: =IF(O12="抖音",ROUND(I12*100,2),ROUND(M12*100,2)) -> 3.44 | S12: =C12&"・"&E12&"【"&Q12&"票"&","&R12&"%"&"】"&P12&"次" -> 安徽合肥凤麟路公司・品越供应链【423票,3.44%】1次
A13: 46221 | B13: 义乌 | C13: 浙江温州洞头区瓯江口公司 | D13: 浙江温州洞头区瓯江口公司瑞鸿菜鸟仓3256866238 | E13: 瑞鸿菜鸟仓 | F13: 3256866238 | G13: 0 | H13: 0 | I13: 0 | J13: 0 | K13: 383 | L13: 383 | M13: 37.77% | N13: 0 | O13: 淘天 | P13: =_xlfn.XLOOKUP(D13,TOP客户累计改善清单!E:E,TOP客户累计改善清单!K:K) -> 1 | Q13: =IF(O13="抖音",H13,L13) -> 383 | R13: =IF(O13="抖音",ROUND(I13*100,2),ROUND(M13*100,2)) -> 37.77 | S13: =C13&"・"&E13&"【"&Q13&"票"&","&R13&"%"&"】"&P13&"次" -> 浙江温州洞头区瓯江口公司・瑞鸿菜鸟仓【383票,37.77%】1次
A14: 46221 | B14: 福建 | C14: 福建涵东公司 | D14: 福建涵东公司朱丽萍的C店459974517700 | E14: 朱丽萍的C店 | F14: 459974517700 | G14: 0 | H14: 0 | I14: 0 | J14: 0 | K14: 522 | L14: 383 | M14: 47.7% | N14: 267 | O14: 淘天 | P14: =_xlfn.XLOOKUP(D14,TOP客户累计改善清单!E:E,TOP客户累计改善清单!K:K) -> 1 | Q14: =IF(O14="抖音",H14,L14) -> 383 | R14: =IF(O14="抖音",ROUND(I14*100,2),ROUND(M14*100,2)) -> 47.7 | S14: =C14&"・"&E14&"【"&Q14&"票"&","&R14&"%"&"】"&P14&"次" -> 福建涵东公司・朱丽萍的C店【383票,47.7%】1次
A15: 46222 | B15: 河北 | C15: 河北南宫市公司 | D15: 河北南宫市公司胜利大街惠-岳世辉-快手追风潮童-抖音光伟童装工厂店-拼多多左左右右童-视频号小可爱童装-淘宝贵泽童装工厂951800650006 | E15: 胜利大街惠-岳世辉-快手追风潮童-抖音光伟童装工厂店-拼多多左左右右童-视频号小可爱童装-淘宝贵泽童装工厂 | F15: 951800650006 | G15: 2198 | H15: 1973 | I15: 34.93% | J15: 195 | K15: 0 | L15: 0 | M15: 0 | N15: 0 | O15: 抖音 | P15: =_xlfn.XLOOKUP(D15,TOP客户累计改善清单!E:E,TOP客户累计改善清单!K:K) -> 2 | Q15: =IF(O15="抖音",H15,L15) -> 1973 | R15: =IF(O15="抖音",ROUND(I15*100,2),ROUND(M15*100,2)) -> 34.93 | S15: =C15&"・"&E15&"【"&Q15&"票"&","&R15&"%"&"】"&P15&"次" -> 河北南宫市公司・胜利大街惠-岳世辉-快手追风潮童-抖音光伟童装工厂店-拼多多左左右右童-视频号小可爱童装-淘宝贵泽童装工厂【1973票,34.93%】2次
A16: 46222 | B16: 苏州 | C16: 江苏苏州常熟市招商城公司 | D16: 江苏苏州常熟市招商城公司聚福-小灰兔681709798994 | E16: 聚福-小灰兔 | F16: 681709798994 | G16: 4369 | H16: 1561 | I16: 4.08% | J16: 158 | K16: 0 | L16: 0 | M16: 0 | N16: 0 | O16: 抖音 | P16: =_xlfn.XLOOKUP(D16,TOP客户累计改善清单!E:E,TOP客户累计改善清单!K:K) -> 1 | Q16: =IF(O16="抖音",H16,L16) -> 1561 | R16: =IF(O16="抖音",ROUND(I16*100,2),ROUND(M16*100,2)) -> 4.08 | S16: =C16&"・"&E16&"【"&Q16&"票"&","&R16&"%"&"】"&P16&"次" -> 江苏苏州常熟市招商城公司・聚福-小灰兔【1561票,4.08%】1次
A17: 46222 | B17: 广佛中 | C17: 广东佛山南海新河村公司 | D17: 广东佛山南海新河村公司公司直营-曼馨抖音珠茉美妆-启能拼多多大赚顺-启能菜鸟tb4336332592572014411986 | E17: 公司直营-曼馨抖音珠茉美妆-启能拼多多大赚顺-启能菜鸟tb4336332592 | F17: 572014411986 | G17: 1559 | H17: 1368 | I17: 16.48% | J17: 103 | K17: 0 | L17: 0 | M17: 0 | N17: 0 | O17: 抖音 | P17: =_xlfn.XLOOKUP(D17,TOP客户累计改善清单!E:E,TOP客户累计改善清单!K:K) -> 2 | Q17: =IF(O17="抖音",H17,L17) -> 1368 | R17: =IF(O17="抖音",ROUND(I17*100,2),ROUND(M17*100,2)) -> 16.48 | S17: =C17&"・"&E17&"【"&Q17&"票"&","&R17&"%"&"】"&P17&"次" -> 广东佛山南海新河村公司・公司直营-曼馨抖音珠茉美妆-启能拼多多大赚顺-启能菜鸟tb4336332592【1368票,16.48%】2次
A18: 46222 | B18: 广佛中 | C18: 广东广州增城市新塘公司红石服务部 | D18: 广东广州增城市新塘公司红石服务部Z-巨野H店-YLS服饰工广店D178289113413 | E18: Z-巨野H店-YLS服饰工广店D | F18: 178289113413 | G18: 1308 | H18: 1198 | I18: 37.94% | J18: 94 | K18: 0 | L18: 0 | M18: 0 | N18: 0 | O18: 抖音 | P18: =_xlfn.XLOOKUP(D18,TOP客户累计改善清单!E:E,TOP客户累计改善清单!K:K) -> 1 | Q18: =IF(O18="抖音",H18,L18) -> 1198 | R18: =IF(O18="抖音",ROUND(I18*100,2),ROUND(M18*100,2)) -> 37.94 | S18: =C18&"・"&E18&"【"&Q18&"票"&","&R18&"%"&"】"&P18&"次" -> 广东广州增城市新塘公司红石服务部・Z-巨野H店-YLS服饰工广店D【1198票,37.94%】1次
A19: 46222 | B19: 苏州 | C19: 江苏常熟东南公司 | D19: 江苏常熟东南公司赵振振-郑贵清专属文艺小铺子138213416669 | E19: 赵振振-郑贵清专属文艺小铺子 | F19: 138213416669 | G19: 1996 | H19: 850 | I19: 39.39% | J19: 10 | K19: 0 | L19: 0 | M19: 0 | N19: 0 | O19: 抖音 | P19: =_xlfn.XLOOKUP(D19,TOP客户累计改善清单!E:E,TOP客户累计改善清单!K:K) -> 2 | Q19: =IF(O19="抖音",H19,L19) -> 850 | R19: =IF(O19="抖音",ROUND(I19*100,2),ROUND(M19*100,2)) -> 39.39 | S19: =C19&"・"&E19&"【"&Q19&"票"&","&R19&"%"&"】"&P19&"次" -> 江苏常熟东南公司・赵振振-郑贵清专属文艺小铺子【850票,39.39%】2次
A20: 46222 | B20: 义乌 | C20: 浙江温州洞头区瓯江口公司 | D20: 浙江温州洞头区瓯江口公司瑞鸿菜鸟仓3256866238 | E20: 瑞鸿菜鸟仓 | F20: 3256866238 | G20: 0 | H20: 0 | I20: 0 | J20: 0 | K20: 564 | L20: 559 | M20: 54.17% | N20: 558 | O20: 淘天 | P20: =_xlfn.XLOOKUP(D20,TOP客户累计改善清单!E:E,TOP客户累计改善清单!K:K) -> 1 | Q20: =IF(O20="抖音",H20,L20) -> 559 | R20: =IF(O20="抖音",ROUND(I20*100,2),ROUND(M20*100,2)) -> 54.17 | S20: =C20&"・"&E20&"【"&Q20&"票"&","&R20&"%"&"】"&P20&"次" -> 浙江温州洞头区瓯江口公司・瑞鸿菜鸟仓【559票,54.17%】1次
A21: 46222 | B21: 山西 | C21: 山西长治潞州区公司 | D21: 山西长治潞州区公司佰鹦汇宠物店548280562641 | E21: 佰鹦汇宠物店 | F21: 548280562641 | G21: 442 | H21: 316 | I21: 39.55% | J21: 1 | K21: 544 | L21: 407 | M21: 43.16% | N21: 0 | O21: 淘天 | P21: =_xlfn.XLOOKUP(D21,TOP客户累计改善清单!E:E,TOP客户累计改善清单!K:K) -> 1 | Q21: =IF(O21="抖音",H21,L21) -> 407 | R21: =IF(O21="抖音",ROUND(I21*100,2),ROUND(M21*100,2)) -> 43.16 | S21: =C21&"・"&E21&"【"&Q21&"票"&","&R21&"%"&"】"&P21&"次" -> 山西长治潞州区公司・佰鹦汇宠物店【407票,43.16%】1次
A22: 46222 | B22: 福建 | C22: 福建石狮市公司永红KH分部 | D22: 福建石狮市公司永红KH分部永红-腾-卖灰机的拖鞋362551220010 | E22: 永红-腾-卖灰机的拖鞋 | F22: 362551220010 | G22: 0 | H22: 0 | I22: 0 | J22: 0 | K22: 352 | L22: 352 | M22: 56.41% | N22: 0 | O22: 淘天 | P22: =_xlfn.XLOOKUP(D22,TOP客户累计改善清单!E:E,TOP客户累计改善清单!K:K) -> 1 | Q22: =IF(O22="抖音",H22,L22) -> 352 | R22: =IF(O22="抖音",ROUND(I22*100,2),ROUND(M22*100,2)) -> 56.41 | S22: =C22&"・"&E22&"【"&Q22&"票"&","&R22&"%"&"】"&P22&"次" -> 福建石狮市公司永红KH分部・永红-腾-卖灰机的拖鞋【352票,56.41%】1次
A23: 46222 | B23: 河南 | C23: 河南虞城县公司李老家乡服务站 | D23: 河南虞城县公司李老家乡服务站马开-开0708786651400300 | E23: 马开-开0708 | F23: 786651400300 | G23: 0 | H23: 0 | I23: 0 | J23: 0 | K23: 356 | L23: 315 | M23: 26.65% | N23: 13 | O23: 淘天 | P23: =_xlfn.XLOOKUP(D23,TOP客户累计改善清单!E:E,TOP客户累计改善清单!K:K) -> 1 | Q23: =IF(O23="抖音",H23,L23) -> 315 | R23: =IF(O23="抖音",ROUND(I23*100,2),ROUND(M23*100,2)) -> 26.65 | S23: =C23&"・"&E23&"【"&Q23&"票"&","&R23&"%"&"】"&P23&"次" -> 河南虞城县公司李老家乡服务站・马开-开0708【315票,26.65%】1次
A24: 46222 | B24: 义乌 | C24: 浙江义乌稠江汇通路公司物流园服务部 | D24: 浙江义乌稠江汇通路公司物流园服务部菜鸟仓c2m----tb62883211322003 | E24: 菜鸟仓c2m----tb6288 | F24: 3211322003 | G24: 0 | H24: 0 | I24: 0 | J24: 0 | K24: 422 | L24: 313 | M24: 0.28% | N24: 164 | O24: 淘天 | P24: =_xlfn.XLOOKUP(D24,TOP客户累计改善清单!E:E,TOP客户累计改善清单!K:K) -> 2 | Q24: =IF(O24="抖音",H24,L24) -> 313 | R24: =IF(O24="抖音",ROUND(I24*100,2),ROUND(M24*100,2)) -> 0.28 | S24: =C24&"・"&E24&"【"&Q24&"票"&","&R24&"%"&"】"&P24&"次" -> 浙江义乌稠江汇通路公司物流园服务部・菜鸟仓c2m----tb6288【313票,0.28%】2次
A25: 46223 | B25: 苏州 | C25: 江苏常熟东南公司 | D25: 江苏常熟东南公司赵振振-郑贵清专属文艺小铺子138213416669 | E25: 赵振振-郑贵清专属文艺小铺子 | F25: 138213416669 | G25: 1810 | H25: 1573 | I25: 80.54% | J25: 52 | K25: 0 | L25: 0 | M25: 0 | N25: 0 | O25: 抖音 | P25: =_xlfn.XLOOKUP(D25,TOP客户累计改善清单!E:E,TOP客户累计改善清单!K:K) -> 2 | Q25: =IF(O25="抖音",H25,L25) -> 1573 | R25: =IF(O25="抖音",ROUND(I25*100,2),ROUND(M25*100,2)) -> 80.54 | S25: =C25&"・"&E25&"【"&Q25&"票"&","&R25&"%"&"】"&P25&"次" -> 江苏常熟东南公司・赵振振-郑贵清专属文艺小铺子【1573票,80.54%】2次
A26: 46223 | B26: 义乌 | C26: 浙江金华金东金义新区公司悦湖分部 | D26: 浙江金华金东金义新区公司悦湖分部常连杰-Pomelosee柚见417738416755 | E26: 常连杰-Pomelosee柚见 | F26: 417738416755 | G26: 1741 | H26: 1572 | I26: 17.43% | J26: 35 | K26: 0 | L26: 0 | M26: 0 | N26: 0 | O26: 抖音 | P26: =_xlfn.XLOOKUP(D26,TOP客户累计改善清单!E:E,TOP客户累计改善清单!K:K) -> 1 | Q26: =IF(O26="抖音",H26,L26) -> 1572 | R26: =IF(O26="抖音",ROUND(I26*100,2),ROUND(M26*100,2)) -> 17.43 | S26: =C26&"・"&E26&"【"&Q26&"票"&","&R26&"%"&"】"&P26&"次" -> 浙江金华金东金义新区公司悦湖分部・常连杰-Pomelosee柚见【1572票,17.43%】1次
A27: 46223 | B27: 苏州 | C27: 江苏苏州常熟市招商城公司 | D27: 江苏苏州常熟市招商城公司聚福-小灰兔681709798994 | E27: 聚福-小灰兔 | F27: 681709798994 | G27: 5333 | H27: 1176 | I27: 2.7% | J27: 217 | K27: 0 | L27: 0 | M27: 0 | N27: 0 | O27: 抖音 | P27: =_xlfn.XLOOKUP(D27,TOP客户累计改善清单!E:E,TOP客户累计改善清单!K:K) -> 1 | Q27: =IF(O27="抖音",H27,L27) -> 1176 | R27: =IF(O27="抖音",ROUND(I27*100,2),ROUND(M27*100,2)) -> 2.7 | S27: =C27&"・"&E27&"【"&Q27&"票"&","&R27&"%"&"】"&P27&"次" -> 江苏苏州常熟市招商城公司・聚福-小灰兔【1176票,2.7%】1次
A28: 46223 | B28: 湖北 | C28: 湖北鄂州华容新葛店公司 | D28: 湖北鄂州华容新葛店公司天门-石总-雅韵阁310571275551 | E28: 天门-石总-雅韵阁 | F28: 310571275551 | G28: 1223 | H28: 1108 | I28: 71.9% | J28: 315 | K28: 0 | L28: 0 | M28: 0 | N28: 0 | O28: 抖音 | P28: =_xlfn.XLOOKUP(D28,TOP客户累计改善清单!E:E,TOP客户累计改善清单!K:K) -> 1 | Q28: =IF(O28="抖音",H28,L28) -> 1108 | R28: =IF(O28="抖音",ROUND(I28*100,2),ROUND(M28*100,2)) -> 71.9 | S28: =C28&"・"&E28&"【"&Q28&"票"&","&R28&"%"&"】"&P28&"次" -> 湖北鄂州华容新葛店公司・天门-石总-雅韵阁【1108票,71.9%】1次
A29: 46223 | B29: 湖北 | C29: 湖北鄂州华容新葛店公司 | D29: 湖北鄂州华容新葛店公司天门-石总-江南女神五店310571429050 | E29: 天门-石总-江南女神五店 | F29: 310571429050 | G29: 3641 | H29: 1022 | I29: 14.56% | J29: 499 | K29: 0 | L29: 0 | M29: 0 | N29: 0 | O29: 抖音 | P29: =_xlfn.XLOOKUP(D29,TOP客户累计改善清单!E:E,TOP客户累计改善清单!K:K) -> 1 | Q29: =IF(O29="抖音",H29,L29) -> 1022 | R29: =IF(O29="抖音",ROUND(I29*100,2),ROUND(M29*100,2)) -> 14.56 | S29: =C29&"・"&E29&"【"&Q29&"票"&","&R29&"%"&"】"&P29&"次" -> 湖北鄂州华容新葛店公司・天门-石总-江南女神五店【1022票,14.56%】1次
A30: 46223 | B30: 山西 | C30: 山西阳高县公司 | D30: 山西阳高县公司山西阳高杏脯店355594302505 | E30: 山西阳高杏脯店 | F30: 355594302505 | G30: 0 | H30: 0 | I30: 0 | J30: 0 | K30: 1498 | L30: 1498 | M30: 100% | N30: 1498 | O30: 淘天 | P30: =_xlfn.XLOOKUP(D30,TOP客户累计改善清单!E:E,TOP客户累计改善清单!K:K) -> 1 | Q30: =IF(O30="抖音",H30,L30) -> 1498 | R30: =IF(O30="抖音",ROUND(I30*100,2),ROUND(M30*100,2)) -> 100 | S30: =C30&"・"&E30&"【"&Q30&"票"&","&R30&"%"&"】"&P30&"次" -> 山西阳高县公司・山西阳高杏脯店【1498票,100%】1次
A31: 46223 | B31: 河南 | C31: 河南新温县公司自营区分部 | D31: 河南新温县公司自营区分部妈妈精品店-百合DD766640565138 | E31: 妈妈精品店-百合DD | F31: 766640565138 | G31: 45 | H31: 44 | I31: 63.77% | J31: 0 | K31: 726 | L31: 726 | M31: 68.62% | N31: 19 | O31: 淘天 | P31: =_xlfn.XLOOKUP(D31,TOP客户累计改善清单!E:E,TOP客户累计改善清单!K:K) -> 1 | Q31: =IF(O31="抖音",H31,L31) -> 726 | R31: =IF(O31="抖音",ROUND(I31*100,2),ROUND(M31*100,2)) -> 68.62 | S31: =C31&"・"&E31&"【"&Q31&"票"&","&R31&"%"&"】"&P31&"次" -> 河南新温县公司自营区分部・妈妈精品店-百合DD【726票,68.62%】1次
A32: 46223 | B32: 贵州 | C32: 贵州习水县公司 | D32: 贵州习水县公司周陆军5646004933 | E32: 周陆军 | F32: 5646004933 | G32: 0 | H32: 0 | I32: 0 | J32: 0 | K32: 531 | L32: 531 | M32: 100% | N32: 0 | O32: 淘天 | P32: =_xlfn.XLOOKUP(D32,TOP客户累计改善清单!E:E,TOP客户累计改善清单!K:K) -> 3 | Q32: =IF(O32="抖音",H32,L32) -> 531 | R32: =IF(O32="抖音",ROUND(I32*100,2),ROUND(M32*100,2)) -> 100 | S32: =C32&"・"&E32&"【"&Q32&"票"&","&R32&"%"&"】"&P32&"次" -> 贵州习水县公司・周陆军【531票,100%】3次
A33: 46223 | B33: 天津 | C33: 天津宝坻区新城公司 | D33: 天津宝坻区新城公司公司自营506045559913 | E33: 公司自营 | F33: 506045559913 | G33: 0 | H33: 0 | I33: 0 | J33: 0 | K33: 494 | L33: 494 | M33: 4.99% | N33: 0 | O33: 淘天 | P33: =_xlfn.XLOOKUP(D33,TOP客户累计改善清单!E:E,TOP客户累计改善清单!K:K) -> 1 | Q33: =IF(O33="抖音",H33,L33) -> 494 | R33: =IF(O33="抖音",ROUND(I33*100,2),ROUND(M33*100,2)) -> 4.99 | S33: =C33&"・"&E33&"【"&Q33&"票"&","&R33&"%"&"】"&P33&"次" -> 天津宝坻区新城公司・公司自营【494票,4.99%】1次
A34: 46223 | B34: 南京 | C34: 江苏徐州铜山区彭城公司 | D34: 江苏徐州铜山区彭城公司乐淘淘873840521933 | E34: 乐淘淘 | F34: 873840521933 | G34: 0 | H34: 0 | I34: 0 | J34: 0 | K34: 361 | L34: 341 | M34: 2.12% | N34: 341 | O34: 淘天 | P34: =_xlfn.XLOOKUP(D34,TOP客户累计改善清单!E:E,TOP客户累计改善清单!K:K) -> 1 | Q34: =IF(O34="抖音",H34,L34) -> 341 | R34: =IF(O34="抖音",ROUND(I34*100,2),ROUND(M34*100,2)) -> 2.12 | S34: =C34&"・"&E34&"【"&Q34&"票"&","&R34&"%"&"】"&P34&"次" -> 江苏徐州铜山区彭城公司・乐淘淘【341票,2.12%】1次
A35: 46224 | B35: 苏州 | C35: 江苏苏州常熟莫城公司 | D35: 江苏苏州常熟莫城公司吴彦祖-陈浩565115100439 | E35: 吴彦祖-陈浩 | F35: 565115100439 | G35: 2211 | H35: 1825 | I35: 33.61% | J35: 281 | K35: 0 | L35: 0 | M35: 0 | N35: 0 | O35: 抖音 | P35: =_xlfn.XLOOKUP(D35,TOP客户累计改善清单!E:E,TOP客户累计改善清单!K:K) -> 3 | Q35: =IF(O35="抖音",H35,L35) -> 1825 | R35: =IF(O35="抖音",ROUND(I35*100,2),ROUND(M35*100,2)) -> 33.61 | S35: =C35&"・"&E35&"【"&Q35&"票"&","&R35&"%"&"】"&P35&"次" -> 江苏苏州常熟莫城公司・吴彦祖-陈浩【1825票,33.61%】3次
A36: 46224 | B36: 河南 | C36: 河南漯河公司召陵镇黄河路中分部 | D36: 河南漯河公司召陵镇黄河路中分部仁聚462534100020 | E36: 仁聚 | F36: 462534100020 | G36: 10630 | H36: 1292 | I36: 2.19% | J36: 41 | K36: 2325 | L36: 621 | M36: 14.1% | N36: 10 | O36: 抖音 | P36: =_xlfn.XLOOKUP(D36,TOP客户累计改善清单!E:E,TOP客户累计改善清单!K:K) -> 2 | Q36: =IF(O36="抖音",H36,L36) -> 1292 | R36: =IF(O36="抖音",ROUND(I36*100,2),ROUND(M36*100,2)) -> 2.19 | S36: =C36&"・"&E36&"【"&Q36&"票"&","&R36&"%"&"】"&P36&"次" -> 河南漯河公司召陵镇黄河路中分部・仁聚【1292票,2.19%】2次
A37: 46224 | B37: 广佛中 | C37: 广东佛山南海新河村公司 | D37: 广东佛山南海新河村公司GJ黄总新-解忧原创手机壳抖音572014996265 | E37: GJ黄总新-解忧原创手机壳抖音 | F37: 572014996265 | G37: 1803 | H37: 1228 | I37: 8.64% | J37: 684 | K37: 0 | L37: 0 | M37: 0 | N37: 0 | O37: 抖音 | P37: =_xlfn.XLOOKUP(D37,TOP客户累计改善清单!E:E,TOP客户累计改善清单!K:K) -> 3 | Q37: =IF(O37="抖音",H37,L37) -> 1228 | R37: =IF(O37="抖音",ROUND(I37*100,2),ROUND(M37*100,2)) -> 8.64 | S37: =C37&"・"&E37&"【"&Q37&"票"&","&R37&"%"&"】"&P37&"次" -> 广东佛山南海新河村公司・GJ黄总新-解忧原创手机壳抖音【1228票,8.64%】3次
A38: 46224 | B38: 深莞惠 | C38: 广东东莞厚街公司 | D38: 广东东莞厚街公司智诚个体店-KH潘总160359819201 | E38: 智诚个体店-KH潘总 | F38: 160359819201 | G38: 2663 | H38: 1226 | I38: 46.02% | J38: 0 | K38: 0 | L38: 0 | M38: 0 | N38: 0 | O38: 抖音 | P38: =_xlfn.XLOOKUP(D38,TOP客户累计改善清单!E:E,TOP客户累计改善清单!K:K) -> 1 | Q38: =IF(O38="抖音",H38,L38) -> 1226 | R38: =IF(O38="抖音",ROUND(I38*100,2),ROUND(M38*100,2)) -> 46.02 | S38: =C38&"・"&E38&"【"&Q38&"票"&","&R38&"%"&"】"&P38&"次" -> 广东东莞厚街公司・智诚个体店-KH潘总【1226票,46.02%】1次
A39: 46224 | B39: 义乌 | C39: 浙江义乌金义都市新区公司菜鸟园分部 | D39: 浙江义乌金义都市新区公司菜鸟园分部常连杰-邱须良品奢企业店896519745234 | E39: 常连杰-邱须良品奢企业店 | F39: 896519745234 | G39: 1471 | H39: 1086 | I39: 11.06% | J39: 21 | K39: 0 | L39: 0 | M39: 0 | N39: 0 | O39: 抖音 | P39: =_xlfn.XLOOKUP(D39,TOP客户累计改善清单!E:E,TOP客户累计改善清单!K:K) -> 1 | Q39: =IF(O39="抖音",H39,L39) -> 1086 | R39: =IF(O39="抖音",ROUND(I39*100,2),ROUND(M39*100,2)) -> 11.06 | S39: =C39&"・"&E39&"【"&Q39&"票"&","&R39&"%"&"】"&P39&"次" -> 浙江义乌金义都市新区公司菜鸟园分部・常连杰-邱须良品奢企业店【1086票,11.06%】1次
A40: 46224 | B40: 河南 | C40: 河南漯河公司召陵镇黄河路中分部 | D40: 河南漯河公司召陵镇黄河路中分部仁聚462534100020 | E40: 仁聚 | F40: 462534100020 | G40: 10630 | H40: 1292 | I40: 2.19% | J40: 41 | K40: 2325 | L40: 621 | M40: 14.1% | N40: 10 | O40: 淘天 | P40: =_xlfn.XLOOKUP(D40,TOP客户累计改善清单!E:E,TOP客户累计改善清单!K:K) -> 2 | Q40: =IF(O40="抖音",H40,L40) -> 621 | R40: =IF(O40="抖音",ROUND(I40*100,2),ROUND(M40*100,2)) -> 14.1 | S40: =C40&"・"&E40&"【"&Q40&"票"&","&R40&"%"&"】"&P40&"次" -> 河南漯河公司召陵镇黄河路中分部・仁聚【621票,14.1%】2次
A41: 46224 | B41: 新疆 | C41: 新疆喀什市公司解放北路分部 | D41: 新疆喀什市公司解放北路分部荒地乡快递驿站844000983623 | E41: 荒地乡快递驿站 | F41: 844000983623 | G41: 0 | H41: 0 | I41: 0 | J41: 0 | K41: 315 | L41: 315 | M41: 100% | N41: 0 | O41: 淘天 | P41: =_xlfn.XLOOKUP(D41,TOP客户累计改善清单!E:E,TOP客户累计改善清单!K:K) -> 1 | Q41: =IF(O41="抖音",H41,L41) -> 315 | R41: =IF(O41="抖音",ROUND(I41*100,2),ROUND(M41*100,2)) -> 100 | S41: =C41&"・"&E41&"【"&Q41&"票"&","&R41&"%"&"】"&P41&"次" -> 新疆喀什市公司解放北路分部・荒地乡快递驿站【315票,100%】1次
A42: 46224 | B42: 杭州 | C42: 浙江杭州萧山区新塘公司 | D42: 浙江杭州萧山区新塘公司红宝石分部-沐洛311420786786 | E42: 红宝石分部-沐洛 | F42: 311420786786 | G42: 0 | H42: 0 | I42: 0 | J42: 0 | K42: 390 | L42: 300 | M42: 6.16% | N42: 63 | O42: 淘天 | P42: =_xlfn.XLOOKUP(D42,TOP客户累计改善清单!E:E,TOP客户累计改善清单!K:K) -> 7 | Q42: =IF(O42="抖音",H42,L42) -> 300 | R42: =IF(O42="抖音",ROUND(I42*100,2),ROUND(M42*100,2)) -> 6.16 | S42: =C42&"・"&E42&"【"&Q42&"票"&","&R42&"%"&"】"&P42&"次" -> 浙江杭州萧山区新塘公司・红宝石分部-沐洛【300票,6.16%】7次
A43: 46224 | B43: 杭州 | C43: 浙江绍兴县钱清公司 | D43: 浙江绍兴县钱清公司郭二杨-8000-鄢志强-T-东方兰旗舰店312521301690 | E43: 郭二杨-8000-鄢志强-T-东方兰旗舰店 | F43: 312521301690 | G43: 0 | H43: 0 | I43: 0 | J43: 0 | K43: 600 | L43: 298 | M43: 27.59% | N43: 58 | O43: 淘天 | P43: =_xlfn.XLOOKUP(D43,TOP客户累计改善清单!E:E,TOP客户累计改善清单!K:K) -> 1 | Q43: =IF(O43="抖音",H43,L43) -> 298 | R43: =IF(O43="抖音",ROUND(I43*100,2),ROUND(M43*100,2)) -> 27.59 | S43: =C43&"・"&E43&"【"&Q43&"票"&","&R43&"%"&"】"&P43&"次" -> 浙江绍兴县钱清公司・郭二杨-8000-鄢志强-T-东方兰旗舰店【298票,27.59%】1次
A44: 46224 | B44: 福建 | C44: 福建涵东公司 | D44: 福建涵东公司豆宝嘟嘟459974517717 | E44: 豆宝嘟嘟 | F44: 459974517717 | G44: 0 | H44: 0 | I44: 0 | J44: 0 | K44: 358 | L44: 295 | M44: 39.6% | N44: 272 | O44: 淘天 | P44: =_xlfn.XLOOKUP(D44,TOP客户累计改善清单!E:E,TOP客户累计改善清单!K:K) -> 1 | Q44: =IF(O44="抖音",H44,L44) -> 295 | R44: =IF(O44="抖音",ROUND(I44*100,2),ROUND(M44*100,2)) -> 39.6 | S44: =C44&"・"&E44&"【"&Q44&"票"&","&R44&"%"&"】"&P44&"次" -> 福建涵东公司・豆宝嘟嘟【295票,39.6%】1次
A45: 46225 | B45: 湖北 | C45: 湖北鄂州华容新葛店公司 | D45: 湖北鄂州华容新葛店公司阳光分部310571361216 | E45: 阳光分部 | F45: 310571361216 | G45: 9504 | H45: 4792 | I45: 0.4839 | J45: 164 | K45: 0 | L45: 0 | M45: 0 | N45: 0 | O45: 抖音 | P45: =_xlfn.XLOOKUP(D45,TOP客户累计改善清单!E:E,TOP客户累计改善清单!K:K) -> 2 | Q45: =IF(O45="抖音",H45,L45) -> 4792 | R45: =IF(O45="抖音",ROUND(I45*100,2),ROUND(M45*100,2)) -> 48.39 | S45: =C45&"・"&E45&"【"&Q45&"票"&","&R45&"%"&"】"&P45&"次" -> 湖北鄂州华容新葛店公司・阳光分部【4792票,48.39%】2次
A46: 46225 | B46: 湖北 | C46: 湖北武汉东西湖走马岭公司优选分部 | D46: 湖北武汉东西湖走马岭公司优选分部兴永商贸767872610012 | E46: 兴永商贸 | F46: 767872610012 | G46: 13023 | H46: 3277 | I46: 0.0299 | J46: 48 | K46: 0 | L46: 0 | M46: 0 | N46: 0 | O46: 抖音 | P46: =_xlfn.XLOOKUP(D46,TOP客户累计改善清单!E:E,TOP客户累计改善清单!K:K) -> 1 | Q46: =IF(O46="抖音",H46,L46) -> 3277 | R46: =IF(O46="抖音",ROUND(I46*100,2),ROUND(M46*100,2)) -> 2.99 | S46: =C46&"・"&E46&"【"&Q46&"票"&","&R46&"%"&"】"&P46&"次" -> 湖北武汉东西湖走马岭公司优选分部・兴永商贸【3277票,2.99%】1次
A47: 46225 | B47: 河南 | C47: 河南漯河公司召陵镇黄河路中分部 | D47: 河南漯河公司召陵镇黄河路中分部仁聚462534100020 | E47: 仁聚 | F47: 462534100020 | G47: 7140 | H47: 2872 | I47: 0.0445 | J47: 2536 | K47: 1983 | L47: 321 | M47: 0.0612 | N47: 54 | O47: 抖音 | P47: =_xlfn.XLOOKUP(D47,TOP客户累计改善清单!E:E,TOP客户累计改善清单!K:K) -> 2 | Q47: =IF(O47="抖音",H47,L47) -> 2872 | R47: =IF(O47="抖音",ROUND(I47*100,2),ROUND(M47*100,2)) -> 4.45 | S47: =C47&"・"&E47&"【"&Q47&"票"&","&R47&"%"&"】"&P47&"次" -> 河南漯河公司召陵镇黄河路中分部・仁聚【2872票,4.45%】2次
A48: 46225 | B48: 福建 | C48: 福建石狮市公司 | D48: 福建石狮市公司凌志-奇尔森从蚂百货优品小铺-全平台362673100261 | E48: 凌志-奇尔森从蚂百货优品小铺-全平台 | F48: 362673100261 | G48: 2216 | H48: 2188 | I48: 0.2826 | J48: 12 | K48: 0 | L48: 0 | M48: 0 | N48: 0 | O48: 抖音 | P48: =_xlfn.XLOOKUP(D48,TOP客户累计改善清单!E:E,TOP客户累计改善清单!K:K) -> 1 | Q48: =IF(O48="抖音",H48,L48) -> 2188 | R48: =IF(O48="抖音",ROUND(I48*100,2),ROUND(M48*100,2)) -> 28.26 | S48: =C48&"・"&E48&"【"&Q48&"票"&","&R48&"%"&"】"&P48&"次" -> 福建石狮市公司・凌志-奇尔森从蚂百货优品小铺-全平台【2188票,28.26%】1次
A49: 46225 | B49: 苏州 | C49: 江苏苏州常熟莫城公司 | D49: 江苏苏州常熟莫城公司吴彦祖-陈浩565115100439 | E49: 吴彦祖-陈浩 | F49: 565115100439 | G49: 1899 | H49: 1684 | I49: 0.3981 | J49: 171 | K49: 0 | L49: 0 | M49: 0 | N49: 0 | O49: 抖音 | P49: =_xlfn.XLOOKUP(D49,TOP客户累计改善清单!E:E,TOP客户累计改善清单!K:K) -> 3 | Q49: =IF(O49="抖音",H49,L49) -> 1684 | R49: =IF(O49="抖音",ROUND(I49*100,2),ROUND(M49*100,2)) -> 39.81 | S49: =C49&"・"&E49&"【"&Q49&"票"&","&R49&"%"&"】"&P49&"次" -> 江苏苏州常熟莫城公司・吴彦祖-陈浩【1684票,39.81%】3次
A50: 46225 | B50: 山西 | C50: 山西阳泉高新区公司 | D50: 山西阳泉高新区公司树直-善良-零食260085657658 | E50: 树直-善良-零食 | F50: 260085657658 | G50: 0 | H50: 0 | I50: 0 | J50: 0 | K50: 443 | L50: 443 | M50: 0.0303 | N50: 443 | O50: 淘天 | P50: =_xlfn.XLOOKUP(D50,TOP客户累计改善清单!E:E,TOP客户累计改善清单!K:K) -> 1 | Q50: =IF(O50="抖音",H50,L50) -> 443 | R50: =IF(O50="抖音",ROUND(I50*100,2),ROUND(M50*100,2)) -> 3.03 | S50: =C50&"・"&E50&"【"&Q50&"票"&","&R50&"%"&"】"&P50&"次" -> 山西阳泉高新区公司・树直-善良-零食【443票,3.03%】1次
A51: 46225 | B51: 北京 | C51: 河北保定徐水区公司安肃镇服务部 | D51: 河北保定徐水区公司安肃镇服务部H张丽君-杨超-K大耳兔保定专卖店T情心好天天500g-轻净家居生活专营店614422100680 | E51: H张丽君-杨超-K大耳兔保定专卖店T情心好天天500g-轻净家居生活专营店 | F51: 614422100680 | G51: 0 | H51: 0 | I51: 0 | J51: 0 | K51: 386 | L51: 385 | M51: 0.7237 | N51: 31 | O51: 淘天 | P51: =_xlfn.XLOOKUP(D51,TOP客户累计改善清单!E:E,TOP客户累计改善清单!K:K) -> 1 | Q51: =IF(O51="抖音",H51,L51) -> 385 | R51: =IF(O51="抖音",ROUND(I51*100,2),ROUND(M51*100,2)) -> 72.37 | S51: =C51&"・"&E51&"【"&Q51&"票"&","&R51&"%"&"】"&P51&"次" -> 河北保定徐水区公司安肃镇服务部・H张丽君-杨超-K大耳兔保定专卖店T情心好天天500g-轻净家居生活专营店【385票,72.37%】1次
A52: 46225 | B52: 杭州 | C52: 浙江杭州萧山区新塘公司 | D52: 浙江杭州萧山区新塘公司红宝石分部-沐洛311420786786 | E52: 红宝石分部-沐洛 | F52: 311420786786 | G52: 0 | H52: 0 | I52: 0 | J52: 0 | K52: 487 | L52: 355 | M52: 0.0823 | N52: 152 | O52: 淘天 | P52: =_xlfn.XLOOKUP(D52,TOP客户累计改善清单!E:E,TOP客户累计改善清单!K:K) -> 7 | Q52: =IF(O52="抖音",H52,L52) -> 355 | R52: =IF(O52="抖音",ROUND(I52*100,2),ROUND(M52*100,2)) -> 8.23 | S52: =C52&"・"&E52&"【"&Q52&"票"&","&R52&"%"&"】"&P52&"次" -> 浙江杭州萧山区新塘公司・红宝石分部-沐洛【355票,8.23%】7次
A53: 46225 | B53: 湖北 | C53: 湖北武汉东西湖走马岭公司优选分部 | D53: 湖北武汉东西湖走马岭公司优选分部梦羊马767872120003 | E53: 梦羊马 | F53: 767872120003 | G53: 299 | H53: 47 | I53: 0.0381 | J53: 0 | K53: 3732 | L53: 349 | M53: 0.0199 | N53: 1 | O53: 淘天 | P53: =_xlfn.XLOOKUP(D53,TOP客户累计改善清单!E:E,TOP客户累计改善清单!K:K) -> 1 | Q53: =IF(O53="抖音",H53,L53) -> 349 | R53: =IF(O53="抖音",ROUND(I53*100,2),ROUND(M53*100,2)) -> 1.99 | S53: =C53&"・"&E53&"【"&Q53&"票"&","&R53&"%"&"】"&P53&"次" -> 湖北武汉东西湖走马岭公司优选分部・梦羊马【349票,1.99%】1次
A54: 46225 | B54: 河南 | C54: 河南巩义市公司 | D54: 河南巩义市公司菜鸟到站取199003105043 | E54: 菜鸟到站取 | F54: 199003105043 | G54: 0 | H54: 0 | I54: 0 | J54: 0 | K54: 386 | L54: 348 | M54: 0.7373 | N54: 245 | O54: 淘天 | P54: =_xlfn.XLOOKUP(D54,TOP客户累计改善清单!E:E,TOP客户累计改善清单!K:K) -> 1 | Q54: =IF(O54="抖音",H54,L54) -> 348 | R54: =IF(O54="抖音",ROUND(I54*100,2),ROUND(M54*100,2)) -> 73.73 | S54: =C54&"・"&E54&"【"&Q54&"票"&","&R54&"%"&"】"&P54&"次" -> 河南巩义市公司・菜鸟到站取【348票,73.73%】1次
A55: 46226 | B55: 河北 | C55: 河北沧州公司沧州服务部 | D55: 河北沧州公司沧州服务部西环-木子李精品女装-胡金维-抖音-视频号102233780588 | E55: 西环-木子李精品女装-胡金维-抖音-视频号 | F55: 102233780588 | G55: 4287 | H55: 3559 | I55: 0.4609 | J55: 165 | K55: 0 | L55: 0 | M55: 0 | N55: 0 | O55: 抖音 | P55: =_xlfn.XLOOKUP(D55,TOP客户累计改善清单!E:E,TOP客户累计改善清单!K:K) -> 1 | Q55: =IF(O55="抖音",H55,L55) -> 3559 | R55: =IF(O55="抖音",ROUND(I55*100,2),ROUND(M55*100,2)) -> 46.09 | S55: =C55&"・"&E55&"【"&Q55&"票"&","&R55&"%"&"】"&P55&"次" -> 河北沧州公司沧州服务部・西环-木子李精品女装-胡金维-抖音-视频号【3559票,46.09%】1次
A56: 46226 | B56: 义乌 | C56: 浙江义乌新光公司 | D56: 浙江义乌新光公司聚财精品好物-X-老付-D3321547548315 | E56: 聚财精品好物-X-老付-D3 | F56: 321547548315 | G56: 2835 | H56: 1475 | I56: 0.1881 | J56: 563 | K56: 0 | L56: 0 | M56: 0 | N56: 0 | O56: 抖音 | P56: =_xlfn.XLOOKUP(D56,TOP客户累计改善清单!E:E,TOP客户累计改善清单!K:K) -> 1 | Q56: =IF(O56="抖音",H56,L56) -> 1475 | R56: =IF(O56="抖音",ROUND(I56*100,2),ROUND(M56*100,2)) -> 18.81 | S56: =C56&"・"&E56&"【"&Q56&"票"&","&R56&"%"&"】"&P56&"次" -> 浙江义乌新光公司・聚财精品好物-X-老付-D3【1475票,18.81%】1次
... A64: 46226 | B64: 深莞惠 | C64: 广东深圳KH公司润樟科技分部 | D64: 广东深圳KH公司润樟科技分部orderoll旗舰店-好古德淘宝509889888600 | E64: orderoll旗舰店-好古德淘宝 | F64: 509889888600 | G64: 0 | H64: 0 | I64: 0 | J64: 0 | K64: 331 | L64: 329 | M64: 0.2544 | N64: 4 | O64: 淘天 | P64: =_xlfn.XLOOKUP(D64,TOP客户累计改善清单!E:E,TOP客户累计改善清单!K:K) -> 1 | Q64: =IF(O64="抖音",H64,L64) -> 329 | R64: =IF(O64="抖音",ROUND(I64*100,2),ROUND(M64*100,2)) -> 25.44 | S64: =C64&"・"&E64&"【"&Q64&"票"&","&R64&"%"&"】"&P64&"次" -> 广东深圳KH公司润樟科技分部・orderoll旗舰店-好古德淘宝【329票,25.44%】1次
A65: 46227 | B65: 湖北 | C65: 湖北鄂州华容新葛店公司 | D65: 湖北鄂州华容新葛店公司阳光分部310571361216 | E65: 阳光分部 | F65: 310571361216 | G65: 16025 | H65: 7464 | I65: 23.71% | J65: 777 | K65: 0 | L65: 0 | M65: 0 | N65: 0 | O65: 抖音 | P65: =_xlfn.XLOOKUP(D65,TOP客户累计改善清单!E:E,TOP客户累计改善清单!K:K) -> 2 | Q65: =IF(O65="抖音",H65,L65) -> 7464 | R65: =IF(O65="抖音",ROUND(I65*100,2),ROUND(M65*100,2)) -> 23.71 | S65: =C65&"・"&E65&"【"&Q65&"票"&","&R65&"%"&"】"&P65&"次" -> 湖北鄂州华容新葛店公司・阳光分部【7464票,23.71%】2次
A66: 46227 | B66: 湖北 | C66: 湖北鄂州华容新葛店公司 | D66: 湖北鄂州华容新葛店公司阳光分部-吴哈的小店310571824665 | E66: 阳光分部-吴哈的小店 | F66: 310571824665 | G66: 4530 | H66: 3465 | I66: 51.09% | J66: 417 | K66: 0 | L66: 0 | M66: 0 | N66: 0 | O66: 抖音 | P66: =_xlfn.XLOOKUP(D66,TOP客户累计改善清单!E:E,TOP客户累计改善清单!K:K) -> 1 | Q66: =IF(O66="抖音",H66,L66) -> 3465 | R66: =IF(O66="抖音",ROUND(I66*100,2),ROUND(M66*100,2)) -> 51.09 | S66: =C66&"・"&E66&"【"&Q66&"票"&","&R66&"%"&"】"&P66&"次" -> 湖北鄂州华容新葛店公司・阳光分部-吴哈的小店【3465票,51.09%】1次
A67: 46227 | B67: 广佛中 | C67: 广东佛山南海新河村公司臻成分部 | D67: 广东佛山南海新河村公司臻成分部GJ黄总新-解忧原创手机壳抖音572014996265 | E67: GJ黄总新-解忧原创手机壳抖音 | F67: 572014996265 | G67: 4314 | H67: 3167 | I67: 9.26% | J67: 1186 | K67: 0 | L67: 0 | M67: 0 | N67: 0 | O67: 抖音 | P67: =_xlfn.XLOOKUP(D67,TOP客户累计改善清单!E:E,TOP客户累计改善清单!K:K) -> 3 | Q67: =IF(O67="抖音",H67,L67) -> 3167 | R67: =IF(O67="抖音",ROUND(I67*100,2),ROUND(M67*100,2)) -> 9.26 | S67: =C67&"・"&E67&"【"&Q67&"票"&","&R67&"%"&"】"&P67&"次" -> 广东佛山南海新河村公司臻成分部・GJ黄总新-解忧原创手机壳抖音【3167票,9.26%】3次
A68: 46227 | B68: 山东 | C68: 山东乐陵市公司 | D68: 山东乐陵市公司鑫香园妙味倾城食品抖音448303100666 | E68: 鑫香园妙味倾城食品抖音 | F68: 448303100666 | G68: 3015 | H68: 3006 | I68: 20.59% | J68: 34 | K68: 0 | L68: 0 | M68: 0 | N68: 0 | O68: 抖音 | P68: =_xlfn.XLOOKUP(D68,TOP客户累计改善清单!E:E,TOP客户累计改善清单!K:K) -> 1 | Q68: =IF(O68="抖音",H68,L68) -> 3006 | R68: =IF(O68="抖音",ROUND(I68*100,2),ROUND(M68*100,2)) -> 20.59 | S68: =C68&"・"&E68&"【"&Q68&"票"&","&R68&"%"&"】"&P68&"次" -> 山东乐陵市公司・鑫香园妙味倾城食品抖音【3006票,20.59%】1次
A69: 46227 | B69: 云南 | C69: 云南昆明五华区小西门公司 | D69: 云南昆明五华区小西门公司明虎食品菌汤包-拼多多抖音快手650005464689 | E69: 明虎食品菌汤包-拼多多抖音快手 | F69: 650005464689 | G69: 2538 | H69: 1653 | I69: 24.22% | J69: 0 | K69: 0 | L69: 0 | M69: 0 | N69: 0 | O69: 抖音 | P69: =_xlfn.XLOOKUP(D69,TOP客户累计改善清单!E:E,TOP客户累计改善清单!K:K) -> 1 | Q69: =IF(O69="抖音",H69,L69) -> 1653 | R69: =IF(O69="抖音",ROUND(I69*100,2),ROUND(M69*100,2)) -> 24.22 | S69: =C69&"・"&E69&"【"&Q69&"票"&","&R69&"%"&"】"&P69&"次" -> 云南昆明五华区小西门公司・明虎食品菌汤包-拼多多抖音快手【1653票,24.22%】1次
A70: 46227 | B70: 广佛中 | C70: 广东佛山南海新河村公司臻成分部 | D70: 广东佛山南海新河村公司臻成分部公司直营-GJ黄总淘宝聚四海科技-GJ黄总DINGP的店快手-CC朱总博瑟雅拼多多-LH桐静小店抖音-LH智通小红书572014398188 | E70: 公司直营-GJ黄总淘宝聚四海科技-GJ黄总DINGP的店快手-CC朱总博瑟雅拼多多-LH桐静小店抖音-LH智通小红书 | F70: 572014398188 | G70: 0 | H70: 0 | I70: 0 | J70: 0 | K70: 677 | L70: 570 | M70: 18.13% | N70: 220 | O70: 淘天 | P70: =_xlfn.XLOOKUP(D70,TOP客户累计改善清单!E:E,TOP客户累计改善清单!K:K) -> 1 | Q70: =IF(O70="抖音",H70,L70) -> 570 | R70: =IF(O70="抖音",ROUND(I70*100,2),ROUND(M70*100,2)) -> 18.13 | S70: =C70&"・"&E70&"【"&Q70&"票"&","&R70&"%"&"】"&P70&"次" -> 广东佛山南海新河村公司臻成分部・公司直营-GJ黄总淘宝聚四海科技-GJ黄总DINGP的店快手-CC朱总博瑟雅拼多多-LH桐静小店抖音-LH智通小红书【570票,18.13%】1次
A71: 46227 | B71: 杭州 | C71: 浙江杭州萧山区新塘公司 | D71: 浙江杭州萧山区新塘公司红宝石分部-沐洛311420786786 | E71: 红宝石分部-沐洛 | F71: 311420786786 | G71: 0 | H71: 0 | I71: 0 | J71: 0 | K71: 600 | L71: 477 | M71: 11.65% | N71: 202 | O71: 淘天 | P71: =_xlfn.XLOOKUP(D71,TOP客户累计改善清单!E:E,TOP客户累计改善清单!K:K) -> 7 | Q71: =IF(O71="抖音",H71,L71) -> 477 | R71: =IF(O71="抖音",ROUND(I71*100,2),ROUND(M71*100,2)) -> 11.65 | S71: =C71&"・"&E71&"【"&Q71&"票"&","&R71&"%"&"】"&P71&"次" -> 浙江杭州萧山区新塘公司・红宝石分部-沐洛【477票,11.65%】7次
A72: 46227 | B72: 河南 | C72: 河南商丘睢阳神火公司路河镇分部 | D72: 河南商丘睢阳神火公司路河镇分部XY-许林峰-深圳市小巴科技-淘宝517508966542 | E72: XY-许林峰-深圳市小巴科技-淘宝 | F72: 517508966542 | G72: 0 | H72: 0 | I72: 0 | J72: 0 | K72: 406 | L72: 405 | M72: 71.55% | N72: 2 | O72: 淘天 | P72: =_xlfn.XLOOKUP(D72,TOP客户累计改善清单!E:E,TOP客户累计改善清单!K:K) -> 1 | Q72: =IF(O72="抖音",H72,L72) -> 405 | R72: =IF(O72="抖音",ROUND(I72*100,2),ROUND(M72*100,2)) -> 71.55 | S72: =C72&"・"&E72&"【"&Q72&"票"&","&R72&"%"&"】"&P72&"次" -> 河南商丘睢阳神火公司路河镇分部・XY-许林峰-深圳市小巴科技-淘宝【405票,71.55%】1次
A73: 46227 | B73: 上海 | C73: 上海青浦区屏新工业区公司 | D73: 上海青浦区屏新工业区公司老蔡店铺a561819557652 | E73: 老蔡店铺a | F73: 561819557652 | G73: 92 | H73: 91 | I73: 10.08% | J73: 88 | K73: 405 | L73: 404 | M73: 22.28% | N73: 402 | O73: 淘天 | P73: =_xlfn.XLOOKUP(D73,TOP客户累计改善清单!E:E,TOP客户累计改善清单!K:K) -> 1 | Q73: =IF(O73="抖音",H73,L73) -> 404 | R73: =IF(O73="抖音",ROUND(I73*100,2),ROUND(M73*100,2)) -> 22.28 | S73: =C73&"・"&E73&"【"&Q73&"票"&","&R73&"%"&"】"&P73&"次" -> 上海青浦区屏新工业区公司・老蔡店铺a【404票,22.28%】1次
A74: 46227 | B74: 山东 | C74: 山东乐陵市公司 | D74: 山东乐陵市公司九棵树方湘食品506394100265 | E74: 九棵树方湘食品 | F74: 506394100265 | G74: 0 | H74: 0 | I74: 0 | J74: 0 | K74: 1179 | L74: 400 | M74: 2.46% | N74: 373 | O74: 淘天 | P74: =_xlfn.XLOOKUP(D74,TOP客户累计改善清单!E:E,TOP客户累计改善清单!K:K) -> 1 | Q74: =IF(O74="抖音",H74,L74) -> 400 | R74: =IF(O74="抖音",ROUND(I74*100,2),ROUND(M74*100,2)) -> 2.46 | S74: =C74&"・"&E74&"【"&Q74&"票"&","&R74&"%"&"】"&P74&"次" -> 山东乐陵市公司・九棵树方湘食品【400票,2.46%】1次

Sheet Sheet2
J15: 发保健品、百货，日均20000单，活动爆单，销量翻倍，缺货，打包动力不足 | K15: 加急备货 加派人手打包
J17: 客户缺货，提前揽收导致 | K17: 网点做始发退回闭环
J19: 发保健品、百货，日均20000单，活动爆单，销量翻倍，缺货，打包动力不足 | K19: 加急备货 加派人手打包
J21: 商家无货提前打单 | K21: 已让网点和客户沟通停止提前打单
J23: 客户缺货 | K23: 缺货商品停止揽收挂预售

Sheet 上榜过且清退过的网点
A1: 一级 | B1: 最近一天限制取号 | C1: 上榜次数 | D1: 清退次数 | H1: 网点名称 | I1: 上级公司名称
A2: 河南商丘睢阳神火公司 | B2: 46209 | C2: 8 | D2: 5 | H2: 北京朝阳区亚运村公司 | I2: 北京朝阳区亚运村公司
A3: 河北韵达鑫通公司 | B3: 46209 | C3: 38 | D3: 3 | H3: 北京昌平区昌平公司 | I3: 北京昌平区昌平公司
A4: 广东深圳公司 | B4: 46198 | C4: 1 | D4: 3 | H4: 北京丰台区腾飞公司 | I4: 北京丰台区腾飞公司
A5: 广东广州天河区渔沙坦公司 | B5: 46196 | C5: 29 | D5: 1 | H5: 北京怀柔区公司 | I5: 北京怀柔区公司
A6: 福建漳州龙海区高新公司 | B6: 46128 | C6: 4 | D6: 1 | H6: 北京密云区公司 | I6: 北京密云区公司
A7: 广东深圳KH公司 | B7: 46109 | C7: 15 | D7: 3 | H7: 北京延庆区公司 | I7: 北京延庆区公司
A8: 湖北天门市公司 | B8: 46100 | C8: 19 | D8: 4 | H8: 北京大兴区龙腾公司 | I8: 北京大兴区龙腾公司
A9: 江西南昌红谷滩新区昌北公司 | B9: 46087 | C9: 3 | D9: 1 | H9: 北京平谷区公司 | I9: 北京平谷区公司
A10: 广东中山富民公司 | B10: 46087 | C10: 1 | D10: 3 | H10: 北京海淀区万寿路公司 | I10: 北京海淀区万寿路公司
A11: 广东广州番禺南村公司 | B11: 46087 | C11: 4 | D11: 3 | H11: 北京西城区百万庄公司 | I11: 北京西城区百万庄公司
A12: 浙江义乌廿三里公司 | B12: 46087 | C12: 8 | D12: 2 | H12: 北京海淀区上地公司 | I12: 北京海淀区上地公司
A13: 浙江金华金东金义新区公司 | B13: 46087 | C13: 4 | D13: 1 | H13: 北京海淀区中关村西北区公司 | I13: 北京海淀区中关村西北区公司
... A47: 河北南宫市公司 | B47: 45207 | C47: 1 | D47: 1 | H47: 北京海淀区安宁庄公司 | I47: 北京海淀区安宁庄公司
H48: 北京丰台区蒲黄榆公司 | I48: 北京丰台区蒲黄榆公司
H49: 华北韵达金韵公司 | I49: 华北韵达金韵公司
H50: 北京朝阳区远洋公司 | I50: 北京朝阳区远洋公司
H51: 北京大兴区工业区公司 | I51: 北京大兴区工业区公司
H52: 北京韵达金韵公司朝阳区伊藤忠分部 | I52: 华北韵达金韵公司
H53: 北京丰台区丰体公司 | I53: 北京丰台区丰体公司
H54: 北京丰台区丰北路公司 | I54: 北京丰台区丰北路公司
H55: 北京大兴区西红门公司 | I55: 北京大兴区西红门公司
H56: 北京丰台区飞宇公司 | I56: 北京丰台区飞宇公司
H57: 北京朝阳区新方庄公司 | I57: 北京朝阳区新方庄公司
H58: 北京朝阳区大营公司 | I58: 北京朝阳区大营公司
H59: 北京朝阳区官庄公司 | I59: 北京朝阳区官庄公司
... H24161: 辽宁沈阳铁西鸿运顺达公司兴华西分部 | I24161: 辽宁沈阳铁西鸿运顺达公司

Sheet Sheet1
A1: 上榜日期 | B1: 省 | C1: 分部名称 | D1: 唯一值（分部名称+客户名称+客户编码 | E1: 客户名称 | F1: 客户编码 | G1: 超时原因 | H1: 整改动作 | I1: 达成日期
A2: 46168 | B2: 深莞惠 | C2: 广东东莞中堂公司文豪分部 | D2: 广东东莞中堂公司文豪分部诺诺潮流服饰抖音-6045370521112998 | E2: 诺诺潮流服饰抖音-6045 | F2: 370521112998 | G2: 客户主售服装类，缺货导致 | H2: 网点已联系客户沟通，三天内整改，客户无改善停止合作 | I2: 46171
A3: 46168 | B3: 江西 | C3: 江西南昌新建区九龙湖公司西客站服务部 | D3: 江西南昌新建区九龙湖公司西客站服务部刘小霞102943623943 | E3: 刘小霞 | F3: 102943623943 | G3: 1.新做的云仓客户，刚搬进来，产品日用品，目前发货1.5万票左右，产品库存不足 | H3: 1.客户缺货要求网点做预售，禁止提前揽收 | I3: 46171
A4: 46168 | B4: 揭阳 | C4: 广东汕头龙湖澄海外砂公司 | D4: 广东汕头龙湖澄海外砂公司(1043海)颂伊-宝趣玩具18d515768570578 | E4: (1043海)颂伊-宝趣玩具18d | F4: 515768570578 | G4: 1.客户突然爆单，部分商品缺货，打包人手不足，导致揽交超时。 | H4: 1.已经通知商家增加人手打包，和厂家对接好，确保货源 。 2.客户缺货的情况下设置预售，禁止提前揽收。 | I4: 46173
A5: 46168 | B5: 新疆 | C5: 新疆和田市公司昆玉分部 | D5: 新疆和田市公司昆玉分部公司策勒客户拓十三零食旗舰店990710300048 | E5: 公司策勒客户拓十三零食旗舰店 | F5: 990710300048 | G5: 距离网点1200公里在途实际需要26个小时，72-96小时特殊考核 | I5: -
A6: 46168 | B6: 广佛中 | C6: 广东广州番禺南村公司朝阳服务部 | D6: 广东广州番禺南村公司朝阳服务部帛卡-法蒙-LaChapelleLC官方旗舰店-天猫抖音695421957175 | E6: 帛卡-法蒙-LaChapelleLC官方旗舰店-天猫抖音 | F6: 695421957175 | G6: 客户爆单缺货 | H6: 始发退回 | I6: 46176
A7: 46168 | B7: 广佛中 | C7: 广东广州白云区大源公司鑫都服务部 | D7: 广东广州白云区大源公司鑫都服务部158133dan-熠宸云仓(2238-小柴)418388101050 | E7: 158133dan-熠宸云仓(2238-小柴) | F7: 418388101050 | G7: 客户爆单缺货 | H7: 始发提回 | I7: 46176
A8: 46168 | B8: 湖北 | C8: 湖北武汉东西湖走马岭公司优选分部 | D8: 湖北武汉东西湖走马岭公司优选分部恒大-大米767872317891 | E8: 恒大-大米 | F8: 767872317891 | G8: 大部分为网点直发未经过分拨 | H8: 未直发发运超时快件联系网点及时对接客户催交 | I8: 46172
A9: 46168 | B9: 四川 | C9: 四川成都金牛五块石公司 | D9: 四川成都金牛五块石公司四川佰河供应链有限公司611534188888 | E9: 四川佰河供应链有限公司 | F9: 611534188888 | G9: 同省礼品件，商家无货做了虚假揽收导致发运超时 | H9: 已经警告商家无货不要做揽收，再次发现关闭该商家的一件揽收功能 | I9: 46172
A10: 46168 | B10: 江西 | C10: 江西南昌青山湖罗家集公司东泰大道服务部 | D10: 江西南昌青山湖罗家集公司东泰大道服务部牛心飞2655031070 | E10: 牛心飞 | F10: 2655031070 | G10: 客户打单后取消订单、内网无任何记录、因配置完美物流导致超时（网点反映取消了完美物流、自动打开了） | H10: 1.已要求网点申请重新取消完美物流配置 2.确定当日取消订单快件、及时做始发退回完结时效 | I10: 46171
A11: 46167 | B11: 揭阳 | C11: 广东汕头龙湖澄海外砂公司 | D11: 广东汕头龙湖澄海外砂公司(1043海)颂伊-宝趣玩具18d515768570578 | E11: (1043海)颂伊-宝趣玩具18d | F11: 515768570578 | G11: 客户打包人手不足，前段时间调整有增加临时工，近期临时工不稳定导致打包人手不足。 | H11: 目前客户找了几家小时工外包公司，先撑过这段时间，客户已经陆续，在招一部分自有的员工。 | I11: 46173
A12: 46167 | B12: 河北 | C12: 河北南宫市公司南宫服务部 | D12: 河北南宫市公司南宫服务部紫冢惠-田冬芳-抖音惠洋夫人围巾-淘宝美夫人围巾-拼多多惠洋夫人围巾-视频号惠熙熙衣帽屋795303500071 | E12: 紫冢惠-田冬芳-抖音惠洋夫人围巾-淘宝美夫人围巾-拼多多惠洋夫人围巾-视频号惠熙熙衣帽屋 | F12: 795303500071 | G12: 客户爆单缺货 | H12: 目前已恢复正常 | I12: 46173
A13: 46167 | B13: 湖北 | C13: 湖北孝感新孝南公司美宜佳分部 | D13: 湖北孝感新孝南公司美宜佳分部TM涛哥-张泼(抖音)787122100594 | E13: TM涛哥-张泼(抖音) | F13: 787122100594 | G13: 客户缺货 | H13: 已联系网点后续无改善，总部驳回完美物流申请 | I13: 46170
A14: 46167 | B14: 广佛中 | C14: 广东广州花都区新雅公司天闽汇服务部 | D14: 广东广州花都区新雅公司天闽汇服务部P03-平价高质-抖音-巫总-杨小芳354001681119 | E14: P03-平价高质-抖音-巫总-杨小芳 | F14: 354001681119 | G14: 缺货 | H14: 网点做始发退回 | I14: 46175
A15: 46167 | B15: 深莞惠 | C15: 广东东莞中堂公司文豪分部 | D15: 广东东莞中堂公司文豪分部诺诺潮流服饰抖音-6045370521112998 | E15: 诺诺潮流服饰抖音-6045 | F15: 370521112998 | G15: 客户主售服装类，缺货导致 | H15: 网点已联系客户沟通，三天内整改，客户无改善停止合作 | I15: 46171
A16: 46167 | B16: 山西 | C16: 山西汾阳市公司 | D16: 山西汾阳市公司玩偶932200472252 | E16: 玩偶 | F16: 932200472252 | G16: 同城件订单未及时签收 | H16: 已通知网点同城件订单揽收后及时签收 | I16: 46170
A17: 46167 | B17: 南京 | C17: 江苏南京浦口区新城公司 | D17: 江苏南京浦口区新城公司凤凰新华书店211149548426 | E17: 凤凰新华书店 | F17: 211149548426 | G17: 客户存在打单后取消订单行为，商家现场扫描直接拦截带回，导致内网无扫描记录，且配置完美物流导致发运超时 | H17: 已通知网点沟通客户，针对发运超时做考核，且关闭完美物流 | I17: 46170
... A28: 46166 | B28: 南京 | C28: 江苏南京浦口区新城公司 | D28: 江苏南京浦口区新城公司凤凰新华书店211149548426 | E28: 凤凰新华书店 | F28: 211149548426 | G28: 客户存在打单后取消订单行为，商家现场扫描直接拦截带回，导致内网无扫描记录，且配置完美物流导致发运超时 | H28: 已通知网点沟通客户，针对发运超时做考核，且关闭完美物流 | I28: 46173
A29: 46166 | B29: 湖北 | C29: 湖北孝感新孝南公司美宜佳分部 | D29: 湖北孝感新孝南公司美宜佳分部YC张庆(顺贤供应链)(淘宝)787122100065 | E29: YC张庆(顺贤供应链)(淘宝) | F29: 787122100065 | G29: 网点直发车未经过分拨 | H29: - | I29: -
A30: 46166 | B30: 河北 | C30: 河北石家庄赞皇县公司 | D30: 河北石家庄赞皇县公司门市下单95005493213 | E30: 门市下单 | F30: 95005493213 | G30: 商家缺货 | H30: 已通知网点负责人跟进客户交货情况 | I30: 46174
A31: 46165 | B31: 广佛中 | C31: 广东佛山南海新河村公司 | D31: 广东佛山南海新河村公司曼馨-业彬护肤专营店328起拉均-臻颜视频号667400325337 | E31: 曼馨-业彬护肤专营店328起拉均-臻颜视频号 | F31: 667400325337 | G31: 美妆客户日均8万票，活动期间13万票，发韵达3万票，平常缺货5%左右，22号客户的供应商生产线故障，23号才将货品给到客户这边打包，导致揽件未交大幅度上涨 | H31: 今天已经恢复正常，已跟客户沟通好后续这种突发状况及时反馈给网点，总部也已同步开通分拨兜底规避物流轨迹超时考核 | I31: 46167
A32: 46165 | B32: 揭阳 | C32: 广东汕头龙湖澄海外砂公司 | D32: 广东汕头龙湖澄海外砂公司(1043海)颂伊-宝趣玩具18d515768570578 | E32: (1043海)颂伊-宝趣玩具18d | F32: 515768570578 | G32: 客户打包人手不足，前段时间调整有增加临时工，近期临时工不稳定导致打包人手不足。 | H32: 目前客户找了几家小时工外包公司，先撑过这段时间，客户已经陆续，在招一部分自有的员工。 | I32: 46203
A33: 46165 | B33: 新疆 | C33: 新疆和田市公司昆玉分部 | D33: 新疆和田市公司昆玉分部公司策勒客户拓十三零食旗舰店990710300048 | E33: 公司策勒客户拓十三零食旗舰店 | F33: 990710300048 | G33: 距离网点1200公里在途实际需要26个小时，72-96小时特殊考核 | I33: -
A34: 46165 | B34: 广佛中 | C34: 广东广州花都区新雅公司镜湖分部 | D34: 广东广州花都区新雅公司镜湖分部P93-古桃女装-抖音-赵总961132100009 | E34: P93-古桃女装-抖音-赵总 | F34: 961132100009 | G34: 服装客户，日均5000票，缺货 | H34: 已开通自动始发退回兜底 | I34: 46168
A35: 46165 | B35: 湖北 | C35: 湖北武汉东西湖走马岭公司优选分部 | D35: 湖北武汉东西湖走马岭公司优选分部兴永商贸767872610012 | E35: 兴永商贸 | F35: 767872610012 | G35: 走马岭直发未经过分拨
A36: 46165 | B36: 内蒙 | C36: 内蒙古察右后旗公司 | D36: 内蒙古察右后旗公司陈少东912846891519 | E36: 陈少东 | F36: 912846891519 | G36: 库房新人提前打单 | H36: 对新人做培训、交不出来的做始发退回 | I36: 46167
A37: 46165 | B37: 天津 | C37: 天津武清区大王古公司大王古寄存点 | D37: 天津武清区大王古公司大王古寄存点河务竹卜湿巾通用账号762280888812 | E37: 河务竹卜湿巾通用账号 | F37: 762280888812 | G37: 客户缺货，提前揽收 | H37: 已和网点负责人沟通，续不再出现此类情况 | I37: -
A38: 46165 | B38: 福建 | C38: 福建涵东公司 | D38: 福建涵东公司zys20089459974517716 | E38: zys20089 | F38: 459974517716 | G38: 服装类客户，无库存，需要工厂生产 | H38: 要求客户缺货不打单，网点不提前揽收 | I38: 46174
A39: 46165 | B39: 深莞惠 | C39: 广东深圳KH公司天地通电讯分部 | D39: 广东深圳KH公司天地通电讯分部lianxinglei518537296547 | E39: lianxinglei | F39: 518537296547 | G39: 客户是因为深圳暴雨影响，交货到集包仓在5.30后，导致滞留延误 | H39: 今天已恢复正常 | I39: 46167
A40: 46165 | B40: 四川 | C40: 四川成都双流KH公司龙潭寺服务部 | D40: 四川成都双流KH公司龙潭寺服务部沧海墙纸729857445555 | E40: 沧海墙纸 | F40: 729857445555 | G40: 初次操作集包，流程不熟悉，设备调试并且新建网格仓离乐至分拨较远；网格仓新上岗司机路途不熟 | H40: 通知集包仓加快设备维护进度和使用熟练度，培养司机熟悉揽货交货位置； | I40: 46170
A41: 46163 | B41: 广西 | C41: 广西南宁江南公司新城服务部 | D41: 广西南宁江南公司新城服务部皆用水果-李庆锋抖音568514800102 | E41: 皆用水果-李庆锋抖音 | F41: 568514800102 | G41: 客户水果质量不好，挑好的发部分未能发出待补货； | H41: 已通知网点负责人跟进客户不要提前打单； | I41: 46167
A42: 46163 | B42: 义乌 | C42: 浙江义乌和兴公司 | D42: 浙江义乌和兴公司公司A-康言生活a帷昕甄选322003726594 | E42: 公司A-康言生活a帷昕甄选 | F42: 322003726594 | G42: 这个客户是卖这个产品的 因为现在这个产品是旺季 厂家生产部过来 发来的都是没组装的 客户打包的时候 需要组装 还要数片数 打包就很慢 导致部分货物当天发不完 | H42: 1，客户增加打包人手 2， 客户现在也在重新找生产组装好的厂家 | I42: 46167
A43: 46163 | B43: 揭阳 | C43: 广东汕头龙湖澄海外砂公司 | D43: 广东汕头龙湖澄海外砂公司(1043海)颂伊-宝趣玩具18d515768570578 | E43: (1043海)颂伊-宝趣玩具18d | F43: 515768570578 | G43: 1.客户突然爆单，部分商品缺货，打包人手不足，导致揽交超时。 | H43: 1.已经通知商家增加人手打包，和厂家对接好，确保货源 。 2.客户缺货的情况下设置预售，禁止提前揽收。 | I43: 46170
A44: 46163 | B44: 广西 | C44: 广西南宁青秀区凤岭公司崇铭服务部 | D44: 广西南宁青秀区凤岭公司崇铭服务部300011淘宝我xxxxxxi京东KSLJD003拼多多馋馋鲜果蔬抖音新红薯基地快手an秀白马视频号馋鲜旺客来313059300011 | E44: 300011淘宝我xxxxxxi京东KSLJD003拼多多馋馋鲜果蔬抖音新红薯基地快手an秀白马视频号馋鲜旺客来 | F44: 313059300011 | G44: 客户已打单缺货未发 | H44: 已通知网点负责人跟进客户不要提前打单； | I44: 46167
A45: 46163 | B45: 青海 | C45: 青海玉树州玉树市公司 | D45: 青海玉树州玉树市公司扎家的小店铺抖音686268111116 | E45: 扎家的小店铺抖音 | F45: 686268111116 | G45: 新对接客户，业务员揽收发运一起操作掉了，业务员操作失误导致超时 | H45: 网点老板已培训业务员 | I45: 46167
A46: 46163 | B46: 河北 | C46: 河北清河县公司 | D46: 河北清河县公司陈彬彬-裴志林-822790954008837682 | E46: 陈彬彬-裴志林-822790 | F46: 954008837682 | G46: 客户缺货 | H46: 已通知网点跟进发货，如未改善关停打单权限 | I46: 46167
A47: 46163 | B47: 广西 | C47: 广西南宁青秀区凤岭公司崇铭服务部 | D47: 广西南宁青秀区凤岭公司崇铭服务部芒果16淘宝txxxxxx3拼多多小胖墩鲜鲜果京东Zz13877623868抖音小胖墩鲜鲜果快手快手用户1745932604491白马视频号星辰海精选优品3130596016 | E47: 芒果16淘宝txxxxxx3拼多多小胖墩鲜鲜果京东Zz13877623868抖音小胖墩鲜鲜果快手快手用户1745932604491白马视频号星辰海精选优品 | F47: 3130596016 | G47: 客户已打单缺货未发 | H47: 已通知网点负责人跟进客户不要提前打单； | I47: 46167
A48: 46163 | B48: 河北 | C48: 河北清河县公司清河分部 | D48: 河北清河县公司清河分部然润甄选店-刘阳-822790211444687597 | E48: 然润甄选店-刘阳-822790 | F48: 211444687597 | G48: 客户缺货 | H48: 已通知网点跟进发货，如未改善关停打单权限 | I48: 46167
A49: 46163 | B49: 湖北 | C49: 湖北武汉东西湖走马岭公司优选分部 | D49: 湖北武汉东西湖走马岭公司优选分部天门武汉鞋迷767872910017 | E49: 天门武汉鞋迷 | F49: 767872910017 | G49: 客户缺货 | H49: 已联系网点后续无改善，总部驳回完美物流申请 | I49: 46167
... A56: 46162 | B56: 福建 | C56: 福建涵东公司 | D56: 福建涵东公司ruostyle459974517714 | E56: ruostyle | F56: 459974517714 | G56: 特殊A货市场不屯货，客户缺货，需要生产，同时因反内卷涨价后客户部分件量流失至同行，缺货占比较大; | H56: 网点已安排市场部现场驻点。督促客户及时打包，缺货不打单，打单不提前揽收 | I56: 46165
A57: 46162 | B57: 新疆 | C57: 乌鲁木齐塔巷二公司 | D57: 乌鲁木齐塔巷二公司子瑞巴巴-李丹0八里店黄会强590408800003 | E57: 子瑞巴巴-李丹0八里店黄会强 | F57: 590408800003 | G57: 该网点属于陕西窗口，不是新疆网点，无法跟进 | H57: - | I57: -
A58: 46162 | B58: 福建 | C58: 福建涵东公司 | D58: 福建涵东公司DREWVOTO旗舰店362521525209 | E58: DREWVOTO旗舰店 | F58: 362521525209 | G58: 特殊A货市场不屯货，客户缺货，需要生产，同时因反内卷涨价后客户部分件量流失至同行，缺货占比较大; | H58: 网点已安排市场部现场驻点。督促客户及时打包，缺货不打单，打单不提前揽收 | I58: 46165
A59: 46162 | B59: 杭州 | C59: 浙江杭州萧山区新塘公司 | D59: 浙江杭州萧山区新塘公司红宝石分部-沐洛311420786786 | E59: 红宝石分部-沐洛 | F59: 311420786786 | G59: 商家没货，提前做揽收 | H59: 已联系网点负责人后续还没有改善就停单 | I59: 46167
A60: 46161 | B60: 河北 | C60: 河北肃宁县公司肃宁服务部 | D60: 河北肃宁县公司肃宁服务部K-抖音快手菜鸟-新kh744574740323 | E60: K-抖音快手菜鸟-新kh | F60: 744574740323 | G60: 客户活动爆单，打包人员不足 | H60: 客户已增加打包人员，网点人员现场跟进 | I60: 46167
A61: 46161 | B61: 新疆 | C61: 新疆和田市公司昆玉分部 | D61: 新疆和田市公司昆玉分部公司策勒客户拓十三零食旗舰店990710300048 | E61: 公司策勒客户拓十三零食旗舰店 | F61: 990710300048 | G61: 分拨距离一级网点1000公里以上，一级网点由分拨串点班车运输，每日到件后12点返回，分部12点后揽收的件，第二天统一拉到一级网点跟车运回分拨，所以物流会滞留6-12小时，返回分拨在途需要20-24小时，导致超时 | H61: 对于400公里外网点，新疆省区统一打48-72小时申请，实际网点客户政策，以打好申请 | I61: 46162
A62: 46161 | B62: 河北 | C62: 河北沧州公司沧州服务部 | D62: 河北沧州公司沧州服务部西环-女装大衣工厂1016-朱金超102233551700 | E62: 西环-女装大衣工厂1016-朱金超 | F62: 102233551700 | G62: 客户缺货 | H62: 客户已停发 | I62: 46167
A63: 46161 | B63: 新疆 | C63: 新疆哈密公司中山北路便民服务站分部 | D63: 新疆哈密公司中山北路便民服务站分部北亩772191899031 | E63: 北亩 | F63: 772191899031 | G63: 哈密除省内件外不经过乌鲁木齐分拨，大部分直发西安，特殊考核申请96小时，按照24-48小时考核均会超时，实际网点客户无异常 | H63: 无 | I63: 46162
A64: 46161 | B64: 广佛中 | C64: 广东广州白云区新白云公司新景服务部 | D64: 广东广州白云区新白云公司新景服务部张新雨-一二三服饰白马-简约潮流优选店抖音-公司102037102064 | E64: 张新雨-一二三服饰白马-简约潮流优选店抖音-公司 | F64: 102037102064 | G64: 服装缺货客户，客户有单无货 | H64: 已沟通网点整改，做发运兜底避免抖音平台罚款 | I64: 46169
A65: 46161 | B65: 河南 | C65: 河南荥阳市公司 | D65: 河南荥阳市公司可爱佳童装450042240210 | E65: 可爱佳童装 | F65: 450042240210 | G65: 此客户为市内件客户，忘记做签收 | H65: 每日核查数据，确保及时签收 | I65: 46165
A66: 46161 | B66: 重庆 | C66: 重庆渝北区中央公园公司 | D66: 重庆渝北区中央公园公司中极韵市场部405359591939 | E66: 中极韵市场部 | F66: 405359591939 | G66: 网点忘记做包进包出 | H66: 告知网点每日关注揽件数据 | I66: 46169
A67: 46161 | B67: 新疆 | C67: 乌鲁木齐塔巷二公司 | D67: 乌鲁木齐塔巷二公司子瑞巴巴-李丹0八里店黄会强590408800003 | E67: 子瑞巴巴-李丹0八里店黄会强 | F67: 590408800003 | G67: 该窗口不属于新疆省区，属于西安营销窗口，不是新疆网点客户，无法管控 | H67: 无 | I67: 46162
A68: 46161 | B68: 新疆 | C68: 乌鲁木齐达利公司 | D68: 乌鲁木齐达利公司子瑞巴巴-李丹0八里店黄会强590408800003 | E68: 子瑞巴巴-李丹0八里店黄会强 | F68: 590408800003 | G68: 该窗口不属于新疆省区，属于西安营销窗口，不是新疆网点客户，无法管控 | H68: 无 | I68: 46162
A69: 46160 | B69: 杭州 | C69: 浙江嘉兴秀洲区洪合公司 | D69: 浙江嘉兴秀洲区洪合公司熊才旺-佐沐衫源头服装314094198021 | E69: 熊才旺-佐沐衫源头服装 | F69: 314094198021 | G69: 商家缺货 | H69: 18号已停发 | I69: 46164
A70: 46160 | B70: 河北 | C70: 河北沧州公司沧州服务部 | D70: 河北沧州公司沧州服务部西环-女装大衣工厂1016-朱金超102233551700 | E70: 西环-女装大衣工厂1016-朱金超 | F70: 102233551700 | G70: 客户爆单缺货 | H70: 已通知客户停发 | I70: 46164
A71: 46160 | B71: 安徽 | C71: 安徽合肥凤麟路公司 | D71: 安徽合肥凤麟路公司品越供应链225317100063 | E71: 品越供应链 | F71: 225317100063 | G71: 此件客户属于云仓发货，每天预计发货6千左右 1.一部分是商家缺货未及时发出， 2.一部分是因揽收后次日交件给分拨，正常十一点之前班车肯定能到，但因为是挂车，一般要排队时间长些。 | H71: 1、已告知网点每日查看数据当天揽收的货，合理安排发车时间及时发出。 2.针对商家缺货的快递，不做揽收记录。 | I71: 46164
A72: 46160 | B72: 北京 | C72: 河北韵达鑫通公司梵希蔓分部 | D72: 河北韵达鑫通公司梵希蔓分部梦梦服装1店-项宇航308665110598 | E72: 梦梦服装1店-项宇航 | F72: 308665110598 | G72: 客户促销，单量增长到1.5万票，包不出来 | H72: 已联系网点，督促客户备货 | I72: 46164
A73: 46160 | B73: 河南 | C73: 河南荥阳市公司 | D73: 河南荥阳市公司可爱佳童装450042240210 | E73: 可爱佳童装 | F73: 450042240210 | G73: 此客户为市内件客户，忘记做签收 | H73: 每日核查数据，确保及时签收 | I73: 46164
A74: 46160 | B74: 湖北 | C74: 湖北武汉东西湖走马岭公司优选分部 | D74: 湖北武汉东西湖走马岭公司优选分部天门武汉鞋迷767872910017 | E74: 天门武汉鞋迷 | F74: 767872910017 | G74: 客户缺货 | H74: 已联系网点后续无改善，总部驳回完美物流申请 | I74: 46167
A75: 46160 | B75: 福建 | C75: 福建涵东公司 | D75: 福建涵东公司DREWVOTO旗舰店362521525209 | E75: DREWVOTO旗舰店 | F75: 362521525209 | G75: 客户部分产品缺货，需要生产，同时因反内卷涨价后客户部分件量流失 | H75: 督促客户增加备货并且转预售方式，减少缺货 | I75: 46162
A76: 46160 | B76: 北京 | C76: 河北韵达金速达公司佳运服务部 | D76: 河北韵达金速达公司佳运服务部批量小单品-淘宝-阿哲潮包-通-崔明哲-XL977236101312 | E76: 批量小单品-淘宝-阿哲潮包-通-崔明哲-XL | F76: 977236101312 | G76: 客户促销，单量增长到10万票，包不出来 | H76: 已限量流处理 | I76: 46164
A77: 46159 | B77: 湖北 | C77: 湖北荆门东宝区公司一马光彩分部 | D77: 湖北荆门东宝区公司一马光彩分部TM-一人服饰-福多多-抖音671436464935 | E77: TM-一人服饰-福多多-抖音 | F77: 671436464935 | G77: 客户缺货 | H77: 已联系网点后续无改善，总部驳回完美物流申请 | I77: 46164
A78: 46159 | B78: 河南 | C78: 河南南阳宛城公司仲景路分部 | D78: 河南南阳宛城公司仲景路分部王宁抖拼淘快小五1798视频号锦艾堂955982100045 | E78: 王宁抖拼淘快小五1798视频号锦艾堂 | F78: 955982100045 | G78: 客户日均14000单左右，16号当天网点自动化设备电箱烧了，无法及时集包发出，造成交件时效延误 | H78: 定期检查保养设备，设备异常及时对接分拨沟通协调集包分流，减少网点交件滞留 | I78: 46162
A79: 46159 | B79: 新疆 | C79: 新疆和田市公司昆玉分部 | D79: 新疆和田市公司昆玉分部公司策勒客户拓十三零食旗舰店990710300048 | E79: 公司策勒客户拓十三零食旗舰店 | F79: 990710300048 | G79: 分拨距离一级网点1000公里以上，一级网点由分拨串点班车运输，每日到件后12点返回，分部12点后揽收的件，第二天统一拉到一级网点跟车运回分拨，所以物流会滞留6-12小时，返回分拨在途需要20-24小时，导致超时 | H79: 对于400公里外网点，新疆省区统一打48-72小时申请，实际网点客户政策，以打好申请 | I79: 46161
A80: 46159 | B80: 河南 | C80: 河南信阳新浉河公司 | D80: 河南信阳新浉河公司金牛小商店464384876759 | E80: 金牛小商店 | F80: 464384876759 | G80: 此客户为市内件客户，忘记做签收 | H80: 每日核查数据，确保及时签收 | I80: 46162
A81: 46159 | B81: 陕西 | C81: 陕西咸阳公司 | D81: 陕西咸阳公司豫征2仓881858100012 | E81: 豫征2仓 | F81: 881858100012 | G81: 商家无货，网点提前揽收，货物未发出 | H81: 沟通网点当天揽收当天发出，商家无货不做提前揽收 | I81: 46164
A82: 46159 | B82: 新疆 | C82: 新疆乌鲁木齐分拨营销市场部 | D82: 新疆乌鲁木齐分拨营销市场部聚鑫汇通仓储-14983038055149 | E82: 聚鑫汇通仓储-149 | F82: 83038055149 | G82: 商家缺货 | H82: 该客户属于市场营销部门客户，已经通知营销部整改，针对有单无货商家禁止打单发出 | I82: 46162
A83: 46159 | B83: 义乌 | C83: 浙江台州路桥区公司 | D83: 浙江台州路桥区公司主店铺-菜鸟-拼多多-抖音-快手-视频号318050172517 | E83: 主店铺-菜鸟-拼多多-抖音-快手-视频号 | F83: 318050172517 | G83: 商家缺货 | H83: 联系网点改善，停止揽收 | I83: 46162
... A138: 46152 | B138: 湖北 | C138: 湖北天门市公司国投运营中心服务部 | D138: 湖北天门市公司国投运营中心服务部南哥2号-GT福多多-抖音430697100406 | E138: 南哥2号-GT福多多-抖音 | F138: 430697100406 | G138: 1、客户缺货；2、网点直发车 | H138: 已做始发退回 | I138: 46160
A139: 46152 | B139: 广佛中 | C139: 广东广州天河区渔沙坦公司 | D139: 广东广州天河区渔沙坦公司张新春-大型女装工厂店抖音---公司006510990808633 | E139: 张新春-大型女装工厂店抖音---公司006 | F139: 510990808633 | G139: 服装缺货客户 | H139: 专员未提供 | I139: -
A140: 46152 | B140: 揭阳 | C140: 广东普宁北公司 | D140: 广东普宁北公司直营206-米多多服装优品892251100105 | E140: 直营206-米多多服装优品 | F140: 892251100105 | G140: 1.客户缺货，有单无货导致。 | H140: 1.昨天开始已经做，无货不揽收动作。 | I140: 46162
A141: 46152 | B141: 河南 | C141: 河南郑州新郑市公司 | D141: 河南郑州新郑市公司小章鱼零食屋450006888856 | E141: 小章鱼零食屋 | F141: 450006888856 | G141: 客户原因，客户打错单子，没有发货 | H141: 已和客户沟通处理 | I141: 46154
A142: 46152 | B142: 贵州 | C142: 贵州遵义新仁怀市公司苍龙街道服务部 | D142: 贵州遵义新仁怀市公司苍龙街道服务部芷若岸丁的小店983759828754 | E142: 芷若岸丁的小店 | F142: 983759828754 | G142: 商家打单后无货，无法及时进行交件，导致发运超时 | H142: 已通知网点督促商家，在无货的情况下，不要提前打单和提前揽收，杜绝揽收超时和发运超时的情况再次发生 | I142: 46157
A143: 46152 | B143: 天津 | C143: 天津南开区新广开公司 | D143: 天津南开区新广开公司张女士杂货铺819572200022 | E143: 张女士杂货铺 | F143: 819572200022 | G143: 时效测试件 | H143: 通知网点换平台操作不要使用抖淘平台做时效测试 | I143: 46157
A144: 46152 | B144: 云南 | C144: 云南昆明官渡区金马路公司 | D144: 云南昆明官渡区金马路公司九希生鲜甄选-何兴付650679557220 | E144: 九希生鲜甄选-何兴付 | F144: 650679557220 | G144: 商家打单无货 | H144: 告知商家后续无货不打单 | I144: 46157
A145: 46152 | B145: 河南 | C145: 河南郑州二七区金星公司西广场分部 | D145: 河南郑州二七区金星公司西广场分部公司账户4500348012 | E145: 公司账户 | F145: 4500348012 | G145: 此客户为市内件客户，忘记做签收 | H145: 每日核查数据，确保及时签收 | I145: 46154
A146: 46152 | B146: 揭阳 | C146: 广东汕头潮南新两英公司 | D146: 广东汕头潮南新两英公司韩依恋企业店-KH-志坚678825848923 | E146: 韩依恋企业店-KH-志坚 | F146: 678825848923 | G146: 1.客户突然爆单，打包人手不足导致揽交发运超时。 | H146: 1.已增加人手预计五天之内解决实际问题。 | I146: 46158
A147: 46151 | B147: 揭阳 | C147: 广东汕头龙湖澄海外砂公司 | D147: 广东汕头龙湖澄海外砂公司(1043海)颂伊官方旗舰店18d515768982616 | E147: (1043海)颂伊官方旗舰店18d | F147: 515768982616 | G147: 1.最近广东雨季，客户部分临时工人员没来上班导致，打包人手不足。 | H147: 1.已经在招正式员工，预计3-8天可以完全调整过来。 | I147: 46159
A148: 46151 | B148: 湖北 | C148: 湖北天门市公司国投运营中心服务部 | D148: 湖北天门市公司国投运营中心服务部南哥2号-GT福多多-抖音430697100406 | E148: 南哥2号-GT福多多-抖音 | F148: 430697100406 | G148: 1、客户缺货；2、网点直发车 | H148: 已联系对应网点及时交件 | I148: 46158
A149: 46151 | B149: 湖北 | C149: 湖北天门市公司国投运营中心服务部 | D149: 湖北天门市公司国投运营中心服务部千千定制女装-GT福多多-抖音430697356525 | E149: 千千定制女装-GT福多多-抖音 | F149: 430697356525 | G149: 1、客户缺货；2、网点直发车 | H149: 已联系对应网点，已停止揽件，数据未跑完 | I149: 46158
A150: 46151 | B150: 揭阳 | C150: 广东汕头潮阳区茂兴公司 | D150: 广东汕头潮阳区茂兴公司蕉树高端定制(9888郭立健)845993100963 | E150: 蕉树高端定制(9888郭立健) | F150: 845993100963 | G150: 1.活动爆单，供货紧张，打包太晚。 | H150: 1.已基本调整好了。 | I150: 46157
A151: 46151 | B151: 广佛中 | C151: 广东广州天河区渔沙坦公司 | D151: 广东广州天河区渔沙坦公司张新春-大型女装工厂店抖音---公司006510990808633 | E151: 张新春-大型女装工厂店抖音---公司006 | F151: 510990808633 | G151: 服装缺货客户 | H151: 沟通做始发退回 | I151: 46159
... A169: 46149 | B169: 安徽 | C169: 安徽蚌埠淮上高新区公司 | D169: 安徽蚌埠淮上高新区公司如意百货233051975459 | E169: 如意百货 | F169: 233051975459 | G169: 商家发的内物是小商品，因缺货导致部分件未及时发出 | H169: 已告知网点每日查看数据当天揽收的货，合理安排发车时间及时发出。 3.针对商家缺货的快递，不做揽收记录。 | I169: 46152
A170: 46149 | B170: 新疆 | C170: 新疆哈密公司中山北路便民服务站分部 | D170: 新疆哈密公司中山北路便民服务站分部北亩772191899031 | E170: 北亩 | F170: 772191899031 | G170: 哈密除省内件外不经过乌鲁木齐分拨，大部分直发西安，特殊考核申请96小时，按照24-48小时考核均会超时，实际网点客户无异常
A171: 46149 | B171: 陕西 | C171: 陕西咸阳公司 | D171: 陕西咸阳公司佳十一恒富欣712000202411 | E171: 佳十一恒富欣 | F171: 712000202411 | G171: ①网点集包发出，未及时发到分拨票左右；②商家无货，网点提前揽收300票左右。 | H171: 督促网点协调该商家，揽收后及时进行交件，出现无货或包装不及时的情况杜绝提前打单和提前揽收问题。 | I171: 46154
A172: 46149 | B172: 福建 | C172: 福建涵东公司 | D172: 福建涵东公司云美美_me362521525220 | E172: 云美美_me | F172: 362521525220 | G172: 莆田市场特殊，不囤货，全天不固定打单，有单无货 | H172: ①要求客户无货不打单，网点打单不揽收； ②客户情况特殊情况下，要求做预售件或优先发个礼品单； ③要求网点尽量在0点后揽收，延后时效 | I172: 46151
A173: 46149 | B173: 义乌 | C173: 浙江义乌稠江汇通路公司极电分部 | D173: 浙江义乌稠江汇通路公司极电分部潘-Tt659856359478-P晋晋吃饱了622998221365 | E173: 潘-Tt659856359478-P晋晋吃饱了 | F173: 622998221365 | G173: 缺货导致超时/部分是直跑未做前段分拨扫描 | H173: 已经及时补货 | I173: 46151
A174: 46148 | B174: 陕西 | C174: 陕西西安雁塔高新公司 | D174: 陕西西安雁塔高新公司客户-速联云储-口罩710007800025 | E174: 客户-速联云储-口罩 | F174: 710007800025 | G174: 商家无货，网点提前揽收 | H174: 督促网点协调该商家，揽收后及时进行交件，出现无货或包装不及时的情况杜绝提前打单和提前揽收问题。 | I174: 46153
A175: 46148 | B175: 湖北 | C175: 湖北天门市公司国投运营中心服务部 | D175: 湖北天门市公司国投运营中心服务部千千定制女装-GT福多多-抖音430697356525 | E175: 千千定制女装-GT福多多-抖音 | F175: 430697356525 | G175: 1、客户缺货；2、网点直发车 | H175: 已联系对应网点，已停止拦截 | I175: 46152
A176: 46148 | B176: 河南 | C176: 河南夏邑县公司尹庄分部 | D176: 河南夏邑县公司尹庄分部SQ-贺改改-安辰生活馆-树树小店视频号-吴润泽476917969206 | E176: SQ-贺改改-安辰生活馆-树树小店视频号-吴润泽 | F176: 476917969206 | G176: 商家爆单，每天发货6万单左右，货品复杂 不好打包， 部分组合商品还出现断货情况 | H176: 商家已调整发货仓库，及时招聘临时工提前准备备货，断货的订单 不在做提前揽收 | I176: 46153
A177: 46148 | B177: 安徽 | C177: 安徽阜阳市公司 | D177: 安徽阜阳市公司穆晓标3-圆脸妹236030990846 | E177: 穆晓标3-圆脸妹 | F177: 236030990846 | G177: 商家发货内物是保健品，每天发货大概在2万票左右，商家储备不足导致部分件发出延迟 | H177: 已告知网点每日查看数据当天揽收的货，合理安排发车时间及时发出。 针对商家缺货的快递，不做揽收记录。 | I177: 46152
A178: 46148 | B178: 广西 | C178: 广西南宁青秀区凤岭公司崇铭服务部 | D178: 广西南宁青秀区凤岭公司崇铭服务部BXG35淘宝axxxxxxx黄拼多多良田生鲜薯园抖音良田万亩生鲜快手香得咧红薯白马视频号吉丰水果优选小红书友鲜旗舰店31305910035 | E178: BXG35淘宝axxxxxxx黄拼多多良田生鲜薯园抖音良田万亩生鲜快手香得咧红薯白马视频号吉丰水果优选小红书友鲜旗舰店 | F178: 31305910035 | G178: 1.客户缺货提前打单； | H178: 已单独对接网点，要求客户无货不打单； | I178: 46152
A179: 46148 | B179: 内蒙 | C179: 内蒙古通辽科尔沁公司 | D179: 内蒙古通辽科尔沁公司个发--抖音新928000928001 | E179: 个发--抖音新 | F179: 928000928001 | G179: 由于商家库房新人打单后未告知发件公司揽收交件，造成延误，已做始发退回兜底 | H179: 已告知商家库房人员及时沟通，以免造成未及时揽收交件 | I179: 46149
A180: 46148 | B180: 陕西 | C180: 陕西咸阳公司 | D180: 陕西咸阳公司佳十一恒富欣712000202411 | E180: 佳十一恒富欣 | F180: 712000202411 | G180: 商家无货，网点提前揽收 | H180: 督促网点协调该商家，揽收后及时进行交件，出现无货或包装不及时的情况杜绝提前打单和提前揽收问题。 | I180: 46153
A181: 46148 | B181: 义乌 | C181: 浙江温州洞头区瓯江口公司 | D181: 浙江温州洞头区瓯江口公司瑞鸿菜鸟仓3256866238 | E181: 瑞鸿菜鸟仓 | F181: 3256866238 | G181: 保税仓查验 海关是要做查验，通过后才放行 | H181: 今天已正常 | I181: 46151
A182: 46148 | B182: 福建 | C182: 福建涵东公司 | D182: 福建涵东公司老妈城459974517711 | E182: 老妈城 | F182: 459974517711 | G182: 莆田市场特殊，不囤货，全天不固定打单，有单无货 | H182: ①要求客户无货不打单，网点打单不揽收；②客户情况特殊情况下，要求做预售件或优先发个礼品单；③要求网点尽量在0点后揽收，延后时效 | I182: 46151
... A184: 46147 | B184: 河北 | C184: 河北深泽县公司 | D184: 河北深泽县公司王宇航-拼多多-萱之爱居家日用专营店-抖音-沐洗家居工厂店-500g581795333446 | E184: 王宇航-拼多多-萱之爱居家日用专营店-抖音-沐洗家居工厂店-500g | F184: 581795333446 | G184: 1、网点交件晚，分拨要求3点前交件，车辆4:48进站 2、分拨北京、广州、山西方向运力不足，无仓位，导致压车未卸 3、4日揽收的件，商家缺货，已通知客户停发 | H184: 要求网点提前交件，针对无改善客户会关停权限，禁止出单 | I184: 46151
A185: 46147 | B185: 河北 | C185: 河北沧州公司沧州服务部 | D185: 河北沧州公司沧州服务部西环-三木女装工厂店-胡金伟-抖音102233203652 | E185: 西环-三木女装工厂店-胡金伟-抖音 | F185: 102233203652 | H185: 已关停客户出单权限 | I185: 46151
A186: 46147 | B186: 北京 | C186: 河北韵达鑫通公司梵希蔓分部 | D186: 河北韵达鑫通公司梵希蔓分部优品女装工厂店2-项宇航308665100436 | E186: 优品女装工厂店2-项宇航 | F186: 308665100436 | G186: 网点交货6米8车辆5日凌晨2点之后达到分拨，到达较晚，分拨未收货，5日下午开机后才揽收 | H186: 按照长短线交件制度考核，与操作沟通，尽量揽收到达较晚的车辆，与客户沟通提前操作，提前交货 | I186: 46149
A187: 46147 | B187: 河北 | C187: 河北深泽县公司 | D187: 河北深泽县公司刘兵-抖音-钱满满小铺子581795333537 | E187: 刘兵-抖音-钱满满小铺子 | F187: 581795333537 | G187: 1、网点交件晚，分拨要求3点前交件，车辆4:48进站 2、分拨北京、广州、山西方向运力不足，无仓位，导致压车未卸 | H187: 要求网点提前交件，针对无改善客户会关停权限，禁止出单 | I187: 46151
A188: 46147 | B188: 广佛中 | C188: 广东佛山南海新河村公司臻成分部 | D188: 广东佛山南海新河村公司臻成分部HC-播乐视界数码旗舰店抖音572014960001 | E188: HC-播乐视界数码旗舰店抖音 | F188: 572014960001 | G188: 手机壳客户，日均2万票，缺货 | H188: 沟通做始发退回 | I188: 46155
...
